Workbook

Sheet COA_Cat
B2: Categ_Key | C2: Acc_Categ_Name | D2: Acc_Cate_Nam_Arb | E2: Corrs_Statment
B3: 1 | C3: Long Term Fixed Assets | D3: الأصول طويلة الأجل | E3: Balance Sheet
B4: 2 | C4: Cash & Cash Eqivlant | D4: أصول متداولة النقدية بالبنوك والصندوق | E4: Balance Sheet
B5: 3 | C5: Current Assets | D5: أصول متداولة | E5: Balance Sheet
B6: 4 | C6: Current Liabilities | D6: الخصوم قصيرة الأجل | E6: Balance Sheet
B7: 5 | C7: Shareholder Equity | D7: حقوق مساهمين | E7: Balance Sheet
B8: 6 | C8: Direct Operating Revenue | D8: المبيعات | E8: Income Statement
B9: 7 | C9: Direct Operating Cost | D9: تكلفة المبيعات | E9: Income Statement
B10: 8 | C10: Admins & Gen Expen | D10: مصروفات أدارية وعمومية | E10: Income Statement

Sheet Itm_Cat
A1: Item_Cat_ID | B1: SAL_EINV_ITEM | C1: Item_Categ | D1: SAL_Acc_Key | E1: PUR_Acc_Key | F1: PUR_EINV_ITEM
A2: 1 | B2: EG-692383735-10007581 | C2: Usering Services - Haring Users & Uniform | D2: 18 | E2: 27
A3: 2 | B3: EG-692383735-100075960 | C3: food and baverage | D3: 18 | E3: 21
A4: 3 | B4: EG-692383735-10007579 | C4: Entertainments Activities & Training | D4: 18 | E4: 28
A5: 4 | B5: EG-692383735-10007579 | C5: Both Production & Interior Decoration | D5: 18 | E5: 24
A6: 5 | B6: EG-692383735-10007579 | C6: Branding Eliments in door & outdoor advertisment customized printed items | D6: 18 | E6: 25
A7: 6 | B7: EG-692383735-10007579 | C7: Sound & Light Equipments | D7: 18 | E7: 29
A8: 7 | B8: EG-692383735-10007579 | C8: Event Photo & Vido documetnery services | D8: 18 | E8: 26
A9: 8 | B9: EG-692383735-10007581 | C9: Incentive House Management Fees | D9: 18 | E9: 18
A10: 9 | B10: EG-692383735-10007605 | C10: transfers & transportation among the event | D10: 18 | E10: 20
A11: 10 | B11: EG-692383735-10007597 | C11: Meeting Rooms & Meeting Area Accomodation | D11: 18 | E11: 22
A12: 11 | B12: EG-692383735-10007597 | C12: Hotel Accomodation | D12: 18 | E12: 22
A13: 12 | B13: EG-692383735-10007597 | C13: Land Arrangments | D13: 18 | E13: 28
... A21: 20 | B21: N/A | C21: Professional Fees | D21: 18 | E21: 33

Sheet COA_Mtble
B2: Acc_Name | C2: Acc_Name_Arb | D2: Acc_Key | E2: Categ_Key
B3: Establishment Cost | C3: ح / مصاريف التأسيس وما قبل التشغيل | D3: 1 | E3: 1
B4: Fixed Assets - Computre & Lap tops | C4: أصول ثابتة - كمبيوتر | D4: 2 | E4: 1
B5: Fixed Assets - Vehicle | C5: ح / اصول طويلة الأجل -سيارات | D5: 3 | E5: 1
B6: Cash at Bank - ENBD Current Account | C6: النقدية بالنبوك والصندوق- جنية مصري | D6: 4 | E6: 2
B7: Cash at Bank - ENBD Euro Account | C7: النقدية بالنبوك والصندوق- يورو | D7: 5 | E7: 2
B8: Cash at Bank - ENBD Saving Account | C8: النقدية بالنبوك والصندوق- جنية مصري توفير | D8: 6 | E8: 2
B9: Cash at Bank - ENBD USD Account | C9: النقدية بالنبوك والصندوق- دولار أمريكي | D9: 7 | E9: 2
B10: Cash in Transit | C10: النقدية بالطريق | D10: 8 | E10: 2
B11: Cash on Hand | C11: النقدية بالصندوق | D11: 9 | E11: 2
B12: CHQ Contra Account | C12: شيكات برسم الدفع | D12: 43 | E12: 3
B13: Accounts Receivables | C13: مدينون وأرصدة عملاء | D13: 10 | E13: 3
B14: Staff Loans & Petty Cash settlement Account | C14: مدينون سلف وعهد العاملين | D14: 11 | E14: 3
... B45: Admin & Gen Expen _Staff Food & Eternal Meeting | C45: مصروفات أدارية وعمومية - مصروفات واجبات وأجتماعات خارجية | D45: 42 | E45: 8

Sheet EINV_Itm_Mtble
A1: Item_Categ | B1: Item_Cat_ID | C1: Einvoice Key Code Name
A2: F&B | B2: 2 | C2: وجبات كاترينج | E2: Code ID | F2: Item Categorg
A3: CARMIN | B3: 18 | C3: 016320/BLEED LINE | E3: 1 | F3: Air Tickets
A4: CARMIN | B4: 18 | C4: AIR FILTER ELEMENT | E4: 2 | F4: Accomodation
A5: CARMIN | B5: 18 | C5: BRAKEPAD WEAR SENSOR | E5: 3 | F5: Transfers
A6: Trans | B6: 9 | C6: خدمات الانتقال | E6: 4 | F6: Avenue Rental Charges
A7: Enter | B7: 3 | C7: إدارة الأعمال والخدمات الاستشارية | E7: 5 | F7: Stage Sound & Light Fixtures
A8: ACC | B8: 11 | C8: خدمات الإقامة المؤقتة | E8: 6 | F8: Catering & Restaurant Services
A9: F&B | B9: 2 | C9: وجبات جاهزة - عبوات متنوعة جاهزة للأكل | E9: 7 | F9: Entertainment & Activities During Events
A10: METPHODOC | B10: 7 | C10: Advertising Services | E10: 8 | F10: Designing & Printing of Advertisement elements
A11: F&B | B11: 2 | C11: مشروبات غير كحولية متنوعة | E11: 9 | F11: Outdoors, Decoration & Boths Execution
A12: Enter | B12: 3 | C12: Entertainment Services | E12: 10 | F12: photo & videoes Documenteries & montage Services
A13: METBRANDEC | B13: 14 | C13: الدوریات المطبوعة | E13: 11 | F13: Ushering Services
A14: METARR | B14: 12 | C14: رحلات وخدمات سياحية | E14: 12 | F14: Giveaways
A15: Enter | B15: 3 | C15: حفلات وشو | E15: 13 | F15: Management Fees
A16: METBRANDEC | B16: 14 | C16: نماذج/أوراق العمل - المطبوعة مسبقاً
A17: METBRANDEC | B17: 14 | C17: خدمات الإعلان
A18: METPHODOC | B18: 7 | C18: تصوير فيديو
A19: METBRANDEC | B19: 14 | C19: دعاية واعلان
A20: BOTHP | B20: 4 | C20: إدارة و تنسيق الأحداث
A21: METARR | B21: 12 | C21: حدمات سياحيه مختلفه
A22: CARENT | B22: 15 | C22: نقل سياحي
A23: F&B | B23: 2 | C23: مجموعات متنوعة من الأغذية/المشروبات/التبغ
A24: METBSEQ | B24: 6 | C24: تأجير أجهزة صوت
A25: METBSEQ | B25: 6 | C25: تأجير أجهزة ومعدات حفلات
A26: METACC | B26: 10 | C26: خدمات الاقامة بالغرف
A27: F&B | B27: 2 | C27: ماكولات متنوعة
... A159: CARMIN | B159: 18 | C159: سيارات خاصه - جولدن

Sheet Bud_Itm_Mtble
A1: Item_Cat | B1: Item_Cat_ID | C1: Bud_Item_Des.
A2: METUSH | B2: 1 | C2: Ushers Totaling of (8F + 7M):
A3: METUSH | B3: 1 | C3: Ushers Uniforms - own black suit with white shirt - scarf for ladies / ties for gents
A4: F&B | B4: 2 | C4: Option A : St. Regis - Steak House
A5: Enter | B5: 3 | C5: Rana Arafa
A6: BOTHP | B6: 4 | C6: Poduim / Presenter Desk (specially designed with acrylic lighted logo)
A7: BOTHP | B7: 4 | C7: Side Banners
A8: BOTHP | B8: 4 | C8: Centerpieces - specially made with battery light / logo
A9: BOTHP | B9: 4 | C9: Branded Qubes (5 X 50cm)
A10: BOTHP | B10: 4 | C10: Branded Qubes (5 X 70cm)
A11: BOTHP | B11: 4 | C11: rental of 4 modern chairs (white) + 3 coffee tables
A12: BOTHP | B12: 4 | C12: Production of : Backwall 3m width X 3m height + wooden 1 logo
A13: BOTHP | B13: 4 | C13: Furniture - 2 bar stools + 1 wide counter table (2m) + on side 1 high table
... A176: Rev | B176: 8 | C176: VAT on Management Fees

Sheet PNR_Mtble
A1: CoCen_Key_ID | B1: PNR_ID | C1: Client ID | D1: Branch | E1: Event Name -Description | F1: Start Date | G1: End Date | H1: Size | I1: Venue | J1: Location | K1: Currancy | L1: Total cost | M1: Customer Name | N1: PO Refrance | O1: Electronic Invoice #
A2: 1 | B2: 9.22.C0002.1 | C2: C0002 | D2: Old Company | E2: Standalone 4 days / 3 nights 30 singles Athnes / Greece | M2: Sovalue
A3: 2 | B3: 9.22.C0002.2 | C3: C0002 | D3: Old Company | E3: Movenpick - SOMA BAY 40 Dubiles | M3: Sovalue
A4: 3 | B4: 1.23.C0006.3 | C4: C0006 | D4: Old Company | E4: Roundtable Meeting - Cairo ; Dusit Thani Hotel - New Cairo | M4: Cisco Systems Egypt Ltd.
A5: 4 | B5: 1.22.C0008.4 | C5: C0008 | D5: Old Company | E5: African Currency Forum 15-19 January, Luxor & Cairo, Egypt | M5: Reconnaissance International
A6: 5 | B6: 1.22.C0001.5 | C6: C0001 | D6: Old Company | E6: Luxor / Pediatric Nutrition Summit | M6: ABBOTT LABORATORIES | N6: 22419 / 22415
A7: 6 | B7: 1.22.C0001.6 | C7: C0001 | D7: Old Company | E7: Breakfast @ Oozy Rest. Beni Swief | M7: ABBOTT LABORATORIES | N7: 22439
A8: 7 | B8: 2.22.C0001.7 | C8: C0001 | D8: Old Company | E8: Lunch @ Lemon Café | M8: ABBOTT LABORATORIES | N8: 22423
A9: 8 | B9: 2.22.C0001.8 | C9: C0001 | D9: Old Company | E9: Lunch @ Sabahe Rest. | M9: ABBOTT LABORATORIES | N9: 23017
A10: 9 | B10: 2.22.C0001.9 | C10: C0001 | D10: Old Company | E10: ADC - Four Seasons 1st Residence | M10: ABBOTT LABORATORIES | N10: 4460
A11: 10 | B11: 3.22.C0001.10 | C11: C0001 | D11: Old Company | E11: Dr. M. Shamy Visa | M11: ABBOTT LABORATORIES | N11: 11029
A12: 11 | B12: 3.22.C0001.11 | C12: C0001 | D12: Old Company | E12: RCOG Ultra Sound - Hilton Heliopolis | M12: ABBOTT LABORATORIES | N12: 23193
A13: 12 | B13: 3.22.C0001.12 | C13: C0001 | D13: Old Company | E13: ART - Steigenbereger Tahrir | M13: ABBOTT LABORATORIES | N13: 23280
A14: 13 | B14: 3.22.C0001.13 | C14: C0001 | D14: Old Company | E14: Women Health - JW Marriott | M14: ABBOTT LABORATORIES | N14: 23512
A15: 14 | B15: 3.22.C0001.14 | C15: C0001 | D15: Old Company | E15: Predi Sure Balance | M15: ABBOTT LABORATORIES | N15: 23547 / 23554 / 23573
A16: 15 | B16: 3.22.C0001.15 | C16: C0001 | D16: Old Company | E16: ANI Meeting - Horus Menia | M16: ABBOTT LABORATORIES | N16: 23712
A17: 16 | B17: 4.22.C0001.16 | C17: C0001 | D17: Old Company | E17: Dr. M. Shamy Visa (accomm + Ticket + visa) | M17: ABBOTT LABORATORIES | N17: 11277
A18: 17 | B18: 4.22.C0001.17 | C18: C0001 | D18: Old Company | E18: MOH Public for Disability | M18: ABBOTT LABORATORIES | N18: 23798
A19: 18 | B19: 5.22.C0001.18 | C19: C0001 | D19: Old Company | E19: Trade SA - Holiday Inn - Cairo | M19: ABBOTT LABORATORIES | N19: 29094
A20: 19 | B20: 5.22.C0001.19 | C20: C0001 | D20: Old Company | E20: ADC - Four Seasons 1st Residence | M20: ABBOTT LABORATORIES | N20: 4479
A21: 20 | B21: 6.22.C0001.20 | C21: C0001 | D21: Old Company | E21: ADC - Alex Steigenberger Cecil | M21: ABBOTT LABORATORIES | N21: 4481
A22: 21 | B22: 6.22.C0001.21 | C22: C0001 | D22: Old Company | E22: Tele Health Conference - Four Seasona Nie | M22: ABBOTT LABORATORIES | N22: 5917
A23: 22 | B23: 6.22.C0001.22 | C23: C0001 | D23: Old Company | E23: Ramez Seddik Accommodation | M23: ABBOTT LABORATORIES | N23: 11390
A24: 23 | B24: 6.22.C0001.23 | C24: C0001 | D24: Old Company | E24: Standalone JW Marriott | M24: ABBOTT LABORATORIES | N24: 24457
A25: 24 | B25: 6.22.C0001.24 | C25: C0001 | D25: Old Company | E25: Standalone JW Marriott | M25: ABBOTT LABORATORIES
A26: 25 | B26: 6.22.C0001.25 | C26: C0001 | D26: Old Company | E26: Fairmont Cairo Standalone | M26: ABBOTT LABORATORIES | N26: 24443
A27: 26 | B27: 7.22.C0001.26 | C27: C0001 | D27: Old Company | E27: ADC - Meridien Airport | M27: ABBOTT LABORATORIES | N27: 4495
A28: 27 | B28: 8.22.C0001.27 | C28: C0001 | D28: Old Company | E28: Abbott EPD Influvac - Semiramis Cairo | M28: ABBOTT LABORATORIES | N28: 24837
A29: 28 | B29: 9.22.C0001.28 | C29: C0001 | D29: Old Company | E29: Abbott EPD Dinner - Babel Rest. | M29: ABBOTT LABORATORIES | N29: 11723
A30: 29 | B30: 9.22.C0001.29 | C30: C0001 | D30: Old Company | E30: Air ticket Luxor + Transfer favor | M30: ABBOTT LABORATORIES | N30: 25127
A31: 30 | B31: 10.22.C0001.30 | C31: C0001 | D31: Old Company | E31: 2 Visas Dubai | M31: ABBOTT LABORATORIES | N31: 11805
A32: 31 | B32: 10.22.C0001.31 | C32: C0001 | D32: Old Company | E32: Luxor Tickets + transfers c/o Dr. Essam Kaoud | M32: ABBOTT LABORATORIES | N32: 25506 /25445
A33: 32 | B33: 11.22.C0001.32 | C33: C0001 | D33: Old Company | E33: Ahmed El- Shafie Transportation to Fayoum Group meeting Haram/Fayoum/Haram 24 Nov 2022 | M33: ABBOTT LABORATORIES | N33: 25733- Dated Nov 18,22
A34: 33 | B34: 11.22.C0001.33 | C34: C0001 | D34: Old Company | E34: ADC Four Seasons 1st Residence | M34: ABBOTT LABORATORIES | N34: 4513
A35: 34 | B35: 11.22.C0001.34 | C35: C0001 | D35: Old Company | E35: Anaa Makarova Transportation Nov. 27 from Airport to Dusit Hotel | M35: ABBOTT LABORATORIES | N35: 12012- Dated Nov 18,22
A36: 35 | B36: 11.22.C0001.35 | C36: C0001 | D36: Old Company | E36: Abbott Advisory board Cairo - November 24 | M36: ABBOTT LABORATORIES | N36: 4513 & 4532 - Dated Sep11 & Oct19 -2022
A37: 36 | B37: 11.22.C0008.36 | C37: C0008 | D37: Old Company | E37: VISA Application Services Athnes / Greece Wif's | M37: Dr. Ahmed Hendy So Value
A38: 37 | B38: 3.23.C0007.37 | C38: C0007 | D38: Old Company | E38: Luxor & Aswan Nile Cruise Mr. Ehab Hanna | M38: Ehab Hanna
A39: 39 | B39: 1.23.C0029.39 | C39: C0029 | D39: Old Company | E39: African Currency Forum 15-19 January, Luxor & Cairo, Egypt | M39: Central Bank Of Egypt (banknote Printing Plant) The Association of African Banknotes and Security Document Printers.
A40: 40 | B40: 4.22.C0010.40 | C40: C0010 | D40: Old Company | E40: ICA Ministerial Meeting & ICCH Confrance October 2022 | M40: GV Developments
A41: 41 | B41: 5.22.C0010.41 | C41: C0010 | D41: Old Company | E41: GV trophies | M41: GV Developments
A42: 42 | B42: 3.22.C0003.42 | C42: C0003 | D42: Old Company | E42: Microsoft Tawer W Ghayar Event | M42: MICROSOFT EGYPT LLC
A43: 45 | B43: 2.22.C0011.45 | C43: C0011 | D43: Old Company | E43: Luxor Meeting Feb 16 | M43: Elixir Pharma
A44: 46 | B44: 3.22.C0011.46 | C44: C0011 | D44: Old Company | E44: Istanbul _anti Infection March | M44: Elixir Pharma
A45: 47 | B45: 12.22.C0001.47 | C45: C0001 | D45: Old Company | E45: Ashraf Kortam Tanta Transportation- Decemeber 22 Cairo/Tanta /Cairo | M45: Abbott EPD | N45: 26110 - December 20, 2022
A46: 48 | B46: 12.22.C0015.48 | C46: C0015 | D46: Old Company | E46: IQS_African_Currency_forum_2022 | M46: IQ Structures s.r.o. | N46: Romena Cermakova mail
A47: 49 | B47: 12.22.C0018.49 | C47: C0018 | D47: Old Company | E47: Sponsor Name - Landqart AG | M47: Landqart AG
A48: 50 | B48: 12.22.C0017.50 | C48: C0017 | D48: Old Company | E48: Meeting Add on Package | M48: De La Rue
A49: 51 | B49: 12.22.C0016.51 | C49: C0016 | D49: Old Company | E49: Meeting Add on Package | M49: Giesecke+Devrient Currency Technology GmbH
A50: 52 | B50: 12.22.C0019.52 | C50: C0019 | D50: Old Company | E50: Meeting Add on Package TV with stand-reception counter | M50: Meta Materials Inc (META®)
A51: 53 | B51: 12.22.C0020.53 | C51: C0020 | D51: Old Company | E51: Meeting Add on Package ===Back wall Printing (4M*240CM)+1 x E01 Lockable Counter+2x E13 Round Glass Table 2+6x 14 White Fabric Chair | M51: Luminescene
A52: 54 | B52: 12.22.C0021.54 | C52: C0021 | D52: Old Company | E52: Meeting Add on Package ===Printing logo for counter+2 glass round tables+The 6 chairs should possibly be the same type as the ones coming with our booth and we would like to have 2 matching tables | M52: JURA SECURITY PRINTING
A53: 55 | B53: 12.22.C0022.55 | C53: C0022 | D53: Old Company | E53: Meeting Add on Package | M53: Koenig & Bauer Banknote Solutions SA
A54: 56 | B54: 12.22.C0023.56 | C54: C0023 | D54: Old Company | E54: Meeting Add on Package | M54: Orell Füssli Ltd
A55: 57 | B55: 12.22.C0024.57 | C55: C0024 | D55: Old Company | E55: Meeting Add on Package | M55: Security Fibres UK African
A56: 58 | B56: 12.22.C0025.58 | C56: C0025 | D56: Old Company | E56: Meeting Add on Package | M56: OBERTHUR FIDUCIAIRE
A57: 59 | B57: 12.22.C0001.59 | C57: C0001 | D57: Old Company | E57: Abbott Transfer -Cairo/Banha/Cairo | M57: Abbott EPD
A58: 60 | B58: 12.22.C0026.60 | C58: C0026 | D58: Old Company | E58: Addation to Existing Boths -Printing backdrop 6*2.4/Side Print 2.4*2.4*2 | M58: Crane Currency
... A61: 63 | B61: 1.23.C0006.63 | C61: C0006 | D61: Old Company | E61: Roundtable Meeting - Cairo ; Dusit Thani Hotel - New Cairo | M61: Cisco Systems Egypt Ltd.
A62: 64 | B62: 2.23.C0001.64 | C62: C0001 | D62: Old Company | E62: Abbott Organized Standalone | M62: Abbott EPD | N62: 272
A63: 65 | B63: 3.23.C0001.65 | C63: C0001 | D63: Old Company | E63: Dar Alfouad Abbott Standlone Event Kimpenski | M63: Abbott ADC | N63: 4555
A64: 66 | B64: 3.23.C0001.66 | C64: C0001 | D64: Old Company | E64: Accomodation & Transportation Dr ahmed Elawa as speaker in EPIC 2023 | M64: Abbott ADC | N64: 4559
A65: 67 | B65: 6.23.C0030.67 | C65: C0030 | D65: Old Company | E65: Leading Digital Groth Confrance June 18 Th -2023 Fourseansons Nille Plaza | M65: Klayy Tech | N65: Proforma Invocie 208
A66: 68 | B66: 6.23.C0003.68 | C66: C0003 | D66: Old Company | E66: Microsoft Bizapps Gov event 70 pax – June 19 @ Chephren meeting room JW Marriott | M66: MICROSOFT EGYPT LLC | N66: #100671918
A67: 69 | B67: 8.23.C0031.69 | C67: C0031 | D67: Old Company | E67: Customers Event 4 days / 3 nights 40 Singles Sharm El Sheikh August 9 - 12 | M67: E- Finance Co
A68: 71 | B68: 10.23.C0031.71 | C68: C0031 | D68: Previous Year Adustments | M68: E Finance | N68: (blank) | O68: 3N4ZTDH7B51MF6BVCT6F6HPH10
A69: 75 | B69: 1.24.C0037.75 | C69: C0037 | D69: CAIRO BRANCH | E69: Crve 50 attendees for coffee breaks / 50 attendees for lunch MS Office - Smart Village | M69: Orion 360 | N69: (blank) | O69: B3SZ6J8SJFM38DATT12969MH10
A70: 76 | B70: 1.24.C0003.76 | C70: C0003 | D70: CAIRO BRANCH | E70: Sedra Office Catering MS Office - Smart Village | M70: MICROSOFT EGYPT LLC | N70: (blank) | O70: 0WJYY6Z5F4X1A8XH8NKE4PMH10
A71: 77 | B71: 1.24.C0003.77 | C71: C0003 | D71: CAIRO BRANCH | E71: JW Marriott Microsoft Internal Workshop JW Marriott | M71: MICROSOFT EGYPT LLC | N71: (blank) | O71: 5H7G22FBF90Y8DQ106SM8ANH10
A72: 78 | B72: 1.24.C0003.78 | C72: C0003 | D72: CAIRO BRANCH | E72: MANYIA WEN Capacity Building Bootcamp in Ismailia for Women Led Startups on 2-3 Feb, 2024 | M72: US-AID | N72: (blank) | O72: F9Z2E22C3C2F2R5S08K2GWNH10
A73: 79 | B73: 3.24.C0031.79 | C73: C0031 | D73: CAIRO BRANCH | E73: MLuxor Steigenberger 50 Singles 4 days / 3 nights | M73: E Finance | N73: (blank) | O73: 1N3WZG7KPA784HY4864YA5RH10
A74: 80 | B74: 3.24.C0003.80 | C74: C0003 | D74: UAE Branch | E74: Microsoft - AI Summit Abdeen Palace | M74: MICROSOFT EGYPT LLC Dubai Office | N74: (blank)
A75: 81 | B75: 3.24.C0038.81 | C75: C0038 | D75: CAIRO BRANCH | E75: MANYIA WEN Capacity Building Bootcamp in Ismailia for Women Led Startups on 2-3 Feb, 2024 | M75: US-AID | N75: (blank) | O75: VZ892YRW8QX6H1J0P0WY6MRH10
A76: 82 | B76: 4.24.C0001.82 | C76: C0001 | D76: CAIRO BRANCH | E76: Abbott ADC Training | M76: Abbott Nutrition | N76: (blank) | O76: N06GSB19DQ60XHB4BXFNWAYH10
A77: 83 | B77: 6.24.C0158.83 | C77: C0158 | D77: UAE Branch | E77: The Brand Machine | M77: The Brand Mechanics | O77: 985.24
A78: 84 | B78: 6.24.C0003.84 | C78: C0003 | D78: CAIRO BRANCH | E78: Microsoft - Family Day 300 | M78: MICROSOFT EGYPT LLC | N78: (blank) | O78: 2WPKX9CDVBPS1X2H2VXTXV1J10
A79: 85 | B79: 9.24.C0003.85 | C79: C0003 | D79: CAIRO BRANCH | E79: Microsoft Kick Off 2024 | M79: MICROSOFT EGYPT LLC | N79: 101114583 | O79: JC9JSE1W23349DD358BTJWAJ10
A80: 86 | B80: 10.24.C0003.86 | C80: C0003 | D80: CAIRO BRANCH | E80: Discovery Day 21 pax Dusit Thani | M80: MICROSOFT EGYPT LLC | N80: 101114208 & 101143252 | O80: C2E19YG5N204RAV043YH1CBJ10
A81: 87 | B81: 10.24.C0159.87 | C81: C0159 | D81: CAIRO BRANCH | E81: Movenpick El Gouna Hotel | M81: Direct Egypt | N81: MEMORANDUM OF UNDERSTANDING Between Incentive House of Egypt & Direct Egypt October 17-20 ‘2024 / 4 days – 3 nights Movenpick Hotel | O81: 6RAQJZCZX2GB1GKQ4MWVD9BJ10
A82: 88 | B82: 10.24.C0006.88 | C82: C0006 | D82: CAIRO BRANCH | E82: Cisco Banking Event Four Seasons Nile Plaza - Cairo | M82: Cisco Systems Egypt Ltd. | N82: EGY000EP575870L | O82: K7QEX2Q377DRVN3P4QJZG6EJ10
A83: 89 | B83: 11.24.C0003.89 | C83: C0003 | D83: Cancelled | E83: Redifine ERP | M83: MICROSOFT EGYPT LLC
A84: 90 | B84: 11.24.C0031.90 | C84: C0031 | D84: CAIRO BRANCH | E84: Booth Production @ Rixos Seagate Sharm EL Sheikh | M84: E Finance | N84: 81/2024 | O84: AB43T7DTF3EZ7YMESY4YWJCJ10
A85: 91 | B85: 12.24.C0006.91 | C85: C0006 | D85: UAE Branch | E85: Webexone Cisco Event | M85: CISCO
A86: 92 | B86: 12.24.C0160.92 | C86: C0160 | D86: UAE Branch | E86: Point Hotel Taksim Istanbul Turkey | M86: VAS & IT VALLY
A87: 93 | B87: 11.24.C0003.93 | C87: C0003 | D87: CAIRO BRANCH | E87: Office Catering November MS Office - Smart Village | M87: MICROSOFT EGYPT LLC | N87: 101187220 | O87: EF9GSVVD0BYBS8W25ADQY4DJ10
A88: 94 | B88: 11.24.C0170.94 | C88: C0170 | D88: CAIRO BRANCH | E88: MS Giveaways AUC | M88: information Technology of Egypt Corporation | N88: P.O.NO.:ITE/400/2024 | O88: K5T9F1WXHZA5J6QHWDE3XPFJ10
A89: 95 | B89: 12.24.C0165.95 | C89: C0165 | D89: UAE Branch | E89: 2.7$ Bedouin Night | M89: EAST WEST ADVE RTISING(L.L.C)
A90: 96 | B90: 12.24.C0003.96 | C90: C0003 | D90: CAIRO BRANCH | E90: Happy Days Co Monky Press Dinner for 25 people for Team outing event for SMC Cairo Hub team | M90: MICROSOFT EGYPT LLC | N90: 101198924 | O90: FQBWRHF4CM1QA811GKEXYSFJ10
A91: 102 | B91: 2.25.C0180.102 | C91: C0180 | D91: UAE Branch | E91: TEAMSTOK FZCO MS AI Tour -Feb 2025 | M91: TEAMSTOK FZCO | N91: UAE MOU.2025 TEAMSTOCK INV UAE 25-000202.25.C0180.102 | O91: INV UAE 25-0002
A92: 103 | B92: 2.25.C0006.103 | C92: C0006 | D92: CAIRO BRANCH | E92: North Africa Team Building Event Movenpick El Gouna Hotel 3 days / 2 nights 28 pax + 12 additional | M92: Cisco Systems Egypt Ltd. | N92: EGY000EP602889L | O92: TBD3K7CBNTN7B7PF4725K2PJ10
A93: 104 | B93: 2.25.C0003.104 | C93: C0003 | D93: CAIRO BRANCH | E93: Dinner for Egypt AI Tour. February 10th, 2025, for Microsoft LT Extended LT | M93: MICROSOFT EGYPT LLC | N93: 101257626 | O93: G7XB0886AG3C1RGVJSQB3FMJ10
A94: 105 | B94: 3.25.C0003.105 | C94: C0003 | D94: CAIRO BRANCH | E94: Microsoft - Education Sector - Sigining Cermony | M94: MICROSOFT EGYPT LLC | N94: 101266470 | O94: 03XXTNPM3AZQSP26ANZW5ZPJ10
A95: 106 | B95: 3.25.C0003.106 | C95: C0003 | D95: CAIRO BRANCH | E95: Microsoft FY25 Ramadan Annual Sohour Laylina restaurant | M95: MICROSOFT EGYPT LLC | N95: 101287687 | O95: 4KED550STPYVAJPCG8407ZPJ10
A96: 107 | B96: 4.25.C0006.107 | C96: C0006 | D96: CAIRO BRANCH | E96: Q3_FY2025_Egypt Cisco Venue Four Seasons Nile Plaza | M96: Cisco Systems Egypt Ltd. | N96: EGY000EP618445L | O96: GTRY4AT1CB3KPA6NX2TYDZRJ10
A97: 108 | B97: 5.25.C0202.108 | C97: C0202 | D97: CAIRO BRANCH | E97: 2025 Kick Off Meeting Noventiq @ Steigenberger Al Cazar | M97: Noventiq | N97: MOU .2025 Kick Off. May ‘2025 / 3days – 2 nights
A98: 109 | B98: 4.25.C0003.109 | C98: C0003 | D98: CAIRO BRANCH | E98: Microsoft 365 Copilot Prompt-a-Thon-Egypt Four Seasons Hotel Cairo at Nile Plaza | M98: MICROSOFT EGYPT LLC | N98: 101294665 | O98: 6W99TJ471SAFWEHCAV28S7SJ10
A99: 110 | B99: 4.25.C0003.110 | C99: C0003 | D99: CAIRO BRANCH | E99: CVP Country Visit Mr. Samer Abu Latif | M99: MICROSOFT EGYPT LLC | N99: 04.25.C0003.110 | O99: 9VH70K8M11HEZJ3PGD5899SJ10
A100: 111 | B100: 2.25.C0180.111 | C100: C0180 | D100: UAE Branch | E100: Microsoft Media Coverage Feb 11'2025 | M100: وليد طارق احمد موافي و شريكة | O100: INV UAE 25-0006
A101: 113 | B101: 7.25.C0006.113 | C101: C0006 | D101: CAIRO BRANCH | E101: CISCO hosting in Cairo for partners on July 4seasons
A102: 112 | B102: 5.25.C0003.112 | C102: C0003 | D102: CAIRO BRANCH | E102: MS Office Cattering
...

Sheet Sup_Mtbl
A1: Ven_ID | B1: Ven_Subled_Name | C1: Sup_Tax_Id | D1: Acc_Key | E1: Cost Center | F1: Relationship_Type | G1: Contact_Person | H1: Contact_Person_Title | I1: Contact_Person_Telephone_number | J1: Beneficiary | K1: Address | L1: Telephone_Number | M1: Email_Addres
A2: Bnk_Exp | B2: Bank Charges | D2: 39 | E2: FinanceCost
A3: Bnk_Trnz | B3: Bank Internal Transfer | D3: 8 | E3: FinanceCost
A4: V0001 | B4: STEIGENBERGER Nile Palace Luxor | C4: 204958482 | D4: 12 | E4: Apply | F4: Operating Vendor
A5: V0002 | B5: NORTH AFRICA FOR SHIPMENT AND NASCO TOURS | C5: 202452735 | D5: 12 | E5: Apply | F5: Operating Vendor
A6: V0003 | B6: LE MERIDIEN CAIRO AIRPORT | D6: 12 | E6: Apply | F6: Operating Vendor
A7: V0004 | B7: Unanmed Prinitng & Stationary Suppler | D7: 12 | E7: Apply | F7: Operating Vendor
A8: V0005 | B8: Movenpick Resort Soma Bay | C8: 286783649 | D8: 12 | E8: Apply | F8: Operating Vendor
A9: V0006 | B9: INTER CO MPANY FOR HOTEL TOURIS | D9: 12 | E9: Apply | F9: Operating Vendor
A10: V0007 | B10: SEMIRAMIS INTERCONTINENTAL | D10: 12 | E10: Apply | F10: Operating Vendor
A11: V0008 | B11: CAIRO MARRIOTT HOTEL | D11: 12 | E11: Apply | F11: Operating Vendor | G11: Engy Rashed | H11: Director of Sales | I11: 01200100014
A12: V0009 | B12: JW MARRIOTT HOTEL | D12: 12 | E12: Apply | F12: Operating Vendor
A13: V0010 | B13: M2 DEVELOPMENTS | D13: 12 | E13: Apply | F13: Operating Vendor
A14: V0011 | B14: Raed shekh | D14: 12 | E14: Apply | F14: Operating Vendor
A15: V0012 | B15: Unknwon | D15: 12 | E15: Apply | F15: Operating Vendor
A16: V0013 | B16: رفعت فتحى رمضان مرسى | D16: 12 | E16: Apply | F16: Operating Vendor
A17: V0014 | B17: Rixos Premium Seagate | C17: 200113720 | D17: 12 | E17: Apply | F17: Operating Vendor | L17: +20 69 3710130
A18: V0015 | B18: Royal Maxim Palace Kempinski | D18: 12 | E18: Apply | F18: Operating Vendor | G18: Ahmed Helmy | H18: Director of Sales | I18: 01119999949
A19: V0016 | B19: Hilton Cairo Heliopolis | D19: 12 | E19: Apply | F19: Operating Vendor | G19: Hossam Shehata | H19: Director of Sales | I19: 01222270655 | K19: URUBA STREET,HELIOPOLIS, CARIO EGYPT | L19: 02-2677730-40
A20: V0017 | B20: Pyramid Turizm IC DIC TIC Film Ve Reklam | D20: 12 | E20: Apply | F20: Operating Vendor | K20: ISTANBUL/TURKY
A21: V0018 | B21: FARAH NILE CRUISE | C21: 349700923 | D21: 12 | E21: Apply | F21: Operating Vendor | J21: Golden Nile Travel Service
A22: V0019 | B22: SAMEH Khalil Thabet Khalil | D22: 12 | E22: Apply | F22: Operating Vendor
A23: V0020 | B23: X-NATION High Technology & Events | C23: 628157576 | D23: 12 | E23: Apply | F23: Operating Vendor | K23: [224B, El Kawthar District - HRG] [Builiding H7, Downtown El Gouna] | L23: [0122 213 2929]
A24: V0021 | B24: NEXT AD-advertising and communications | C24: 540224502 | D24: 12 | E24: Apply | F24: Operating Vendor
A25: V0022 | B25: Jolie Ville Hotel Luxor | D25: 12 | E25: Apply | F25: Operating Vendor | G25: Wael Ragaay | H25: Director of Sales | I25: 01000480780
A26: V0023 | B26: Nile Air | D26: 12 | E26: Apply | F26: Operating Vendor
A27: V0024 | B27: SALMA ABDULLAH | D27: 12 | E27: Apply | F27: Operating Vendor
A28: V0025 | B28: Ahmed Mahmoud Aly Mohamed Barakat Photo grapher | C28: 623767406 | D28: 12 | E28: Apply | F28: Operating Vendor
A29: V0026 | B29: Jack Zakaria - DJ | D29: 12 | E29: Apply | F29: Operating Vendor
A30: V0027 | B30: Comtech Egypt Audio Visual Event Management | C30: 672422425 | D30: 12 | E30: Apply | F30: Operating Vendor
A31: V0028 | B31: Fairmont Nile City | D31: 12 | E31: Apply | F31: Operating Vendor
A32: V0029 | B32: Jonathan Cohen -Azimuth Marketing Communications | D32: 12 | E32: Apply | F32: Operating Vendor
A33: V0030 | B33: USHERS ACF | D33: 12 | E33: Apply | F33: Operating Vendor
A34: V0031 | B34: Music Life - Kahlied Al sahfi (Harfosh) | C34: 724028730 | D34: 12 | E34: Apply | F34: Operating Vendor
A35: V0032 | B35: Dusit Thani LakeView Cairo | C35: 301203199 | D35: 12 | E35: Apply | F35: Operating Vendor
A36: V0033 | B36: AIR CAIRO | D36: 12 | E36: Apply | F36: Operating Vendor
A37: V0034 | B37: Grand Nile Tower | D37: 12 | E37: Apply | F37: Operating Vendor | G37: Amira Salim
A38: V0035 | B38: Kempinski Nile Hotel Cairo | C38: 489481132 | D38: 12 | E38: Apply | F38: Operating Vendor
A39: V0036 | B39: Orange Telecom | D39: 12 | E39: Office Sustain Expenses | F39: Operating Vendor
A40: V0037 | B40: ENBD-EGP | D40: 12 | E40: FinanceCost | F40: Operating Vendor
A41: V0038 | B41: Escapade Terval | D41: 12 | E41: Apply | F41: Operating Vendor
A42: V0039 | B42: CRYSTAL ASFOUR | C42: 509184316 | D42: 12 | E42: Apply | F42: Operating Vendor
A43: V0040 | B43: CRYSTAL ASFOUR | C43: 210456035 | D43: 12 | E43: Apply | F43: Operating Vendor
A44: V0041 | B44: Royal Pyramids Diving Center | D44: 12 | E44: Apply | F44: Operating Vendor
A45: V00411 | B45: BTECH MAX | D45: 2 | E45: IT & Computer Devises Lap tops | F45: Service Provider | G45: POS Payent
A46: V0042 | B46: Sofitel Legend Old Cataract Aswan | D46: 12 | E46: Apply | F46: Operating Vendor
A47: V0043 | B47: KANJA | D47: 12 | E47: Apply | F47: Operating Vendor
A48: V0044 | B48: Omina IT | D48: 12 | E48: Apply | F48: Operating Vendor | G48: Omina IT | H48: Vodaphone Cash Paymnet | I48: +20 101 008 7418
A49: V0047 | B49: PARK REGENCY RESORT | C49: 204905923 | D49: 12 | E49: Apply | F49: Operating Vendor
A50: V0048 | B50: TEZ TOUR | C50: 234920076 | D50: 12 | E50: Apply | F50: Operating Vendor
A51: V0049 | B51: SUN & FUN | D51: 12 | E51: Apply | F51: Operating Vendor
A52: V0050 | B52: Egypt Air | C52: 308618343 | D52: 12 | E52: Apply | F52: Operating Vendor
A53: V0051 | B53: Zo Technology IT | C53: 648200973 | D53: 12 | E53: Apply | F53: Operating Vendor
A54: V0052 | B54: ZEEYARA | C54: 601654587 | D54: 12 | E54: Apply | F54: Operating Vendor
A55: V0053 | B55: Steigenberger Alcazar | C55: 204963036 | D55: 12 | E55: Apply | F55: Operating Vendor
A56: V0054 | B56: SEDRA | C56: 200244280 | D56: 12 | E56: Apply | F56: Operating Vendor
A57: V0055 | B57: S&A Advertising | C57: 711038376 | D57: 12 | E57: Apply | F57: Operating Vendor
A58: V0057 | B58: Production House | C58: 672769069 | D58: 12 | E58: Apply | F58: Operating Vendor
A59: V0058 | B59: PENTA VALUE | C59: 498788687 | D59: 12 | E59: Apply | F59: Operating Vendor
A60: V0059 | B60: PATCHI Concept for chocolate & Gifts | C60: 200277847 | D60: 12 | E60: Apply | F60: Operating Vendor
A61: V0060 | B61: Movenpick Resort & Spa El Gouna | C61: 204904153 | D61: 12 | E61: Apply | F61: Operating Vendor
A62: V0061 | B62: Momento Iman Thaha Naouf | C62: 413181553 | D62: 12 | E62: Apply | F62: Operating Vendor
A63: V0062 | B63: MOHEB MAKRAM TRADING | C63: 463469720 | D63: 12 | E63: Apply | F63: Operating Vendor
... A66: V0065 | B66: Khalied Said Charter Accountant | C66: 235011304 | D66: 12 | E66: Apply | F66: Operating Vendor
A67: V0066 | B67: CHILLOUT | D67: 38 | E67: Apply | F67: Service Provider | G67: POS Payent
A68: V0067 | B68: JW Marriott Hotel Cairo | C68: 200201786 | D68: 12 | E68: Apply | F68: Operating Vendor
A69: V0068 | B69: Intercontinental City stars | C69: 208407898 | D69: 12 | E69: Apply | F69: Operating Vendor
A70: V0069 | B70: IKA | C70: 376501170 | D70: 12 | E70: Apply | F70: Operating Vendor
A71: V0070 | B71: Hedeya Giveawys | C71: 479657874 | D71: 12 | E71: Apply | F71: Operating Vendor
A72: V0071 | B72: Happy Days Co Monky Press | C72: 672412799 | D72: 12 | E72: Apply | F72: Operating Vendor
A73: V0072 | B73: Graphic Box | C73: 713633875 | D73: 12 | E73: Apply | F73: Operating Vendor
A74: V0073 | B74: GIG AUTO Insurnace | C74: 200026925 | D74: 12 | E74: Mercedes-Benz -Assets592.ق.ط.ب | F74: Operating Vendor
A75: V0074 | B75: GERMAN AUTO SERVICES | C75: 200143077 | D75: 12 | E75: Mercedes-Benz -Assets592.ق.ط.ب | F75: Operating Vendor
A76: V0075 | B76: Four Seasons Hotel Cairo at Nile Plaza | C76: 204899222 | D76: 12 | E76: Apply | F76: Operating Vendor
A77: V0076 | B77: EVINTI | C77: 447593722 | D77: 12 | E77: Apply | F77: Operating Vendor
A78: V0077 | B78: Event Full | C78: 467158665 | D78: 12 | E78: Apply | F78: Operating Vendor
A79: V0078 | B79: EL KABABGY Sofitel | C79: 100273092 | D79: 12 | E79: Apply | F79: Operating Vendor
A80: V0079 | B80: Egypt trust - Branch | C80: 274264323 | D80: 12 | E80: Office Sustain Expenses | F80: Operating Vendor
A81: V0080 | B81: E Studio | C81: 609091999 | D81: 12 | E81: Apply | F81: Operating Vendor | G81: Ahmed Essam | I81: +20 10 24898117 | K81: 44 El Tayaran St., Nasr City - Cairo, 2nd District Nasr City, Cairo, Egypt
A82: V0081 | B82: Ducks- EGYPTIAN SAUDI FOR TRADING AN D FOOD | C82: 381144542 | D82: 12 | E82: Apply | F82: Operating Vendor
A83: V0082 | B83: DEAL COMPAMY | C83: 418711844 | D83: 12 | E83: Apply | F83: Operating Vendor
A84: V0085 | B84: Crave | C84: 100270530 | D84: 12 | E84: Apply | F84: Operating Vendor
A85: V0087 | B85: CARNIVAL SAMEH Egyptian Art for Show | C85: 552569275 | D85: 12 | E85: Apply | F85: Operating Vendor
A86: V0088 | B86: CAIRO Trade | C86: 679992278 | D86: 12 | E86: Apply | F86: Operating Vendor
A87: V0089 | B87: CAIRO MARRIOTT HOTEL | C87: 100270743 | D87: 12 | E87: Apply | F87: Operating Vendor
A88: V0090 | B88: BAYT WARD | C88: 474962733 | D88: 12 | E88: Apply | F88: Operating Vendor
A89: V0091 | B89: B. Brand | C89: 435382799 | D89: 12 | E89: Apply | F89: Operating Vendor
A90: V0092 | B90: Aspire for Traning | C90: 272098558 | D90: 12 | E90: Apply | F90: Operating Vendor
A91: V0093 | B91: ASHRAF AHMED EBRAHIM | C91: 286483785 | D91: 12 | E91: Office Sustain Expenses | F91: Operating Vendor
A92: V0094 | B92: Ariz | C92: 584664052 | D92: 12 | E92: Apply | F92: Operating Vendor
A93: V0095 | B93: Alternative | C93: 626371988 | D93: 12 | E93: Apply | F93: Operating Vendor
... A97: V0099 | B97: megumi restaurant | C97: 609001744 | D97: 12 | E97: Apply | F97: Operating Vendor
A98: V0100 | B98: B2B office Spaces | D98: 12 | E98: Apply | F98: Service Provider
A99: V0101 | B99: GODADDY | D99: 12 | E99: IT & Computer Devises Lap tops | F99: Service Provider
A100: V0102 | B100: Phd. Najeeb Osman Ayoup | D100: 12 | E100: Office Sustain Expenses | F100: Service Provider
A101: V0103 | B101: North Cairo Electricity distribution | D101: 12 | E101: Office Sustain Expenses | F101: Service Provider
A102: V0104 | B102: WE & Orange Telecommunications | D102: 12 | E102: Office Sustain Expenses | F102: Service Provider
A103: V0105 | B103: Grocery & Catering Supermarkets | D103: 12 | E103: Office Sustain Expenses | F103: Service Provider
A104: V0106 | B104: AMIR SAMI EL GHAZOLY | D104: 12 | E104: Office Sustain Expenses | F104: Service Provider
A105: V0107 | B105: YES SPACE | D105: 12 | E105: Office Sustain Expenses | F105: Service Provider | G105: Heba Solyman
...

Sheet Clnt_Mtbl
A1: Clnt_ID | B1: Clnt_Subled_Name | C1: Clnt_Tax_Id | D1: Acc_Key | E1: Client Address | F1: Telephone Number | G1: Contact Person | H1: Email Address
A2: C0001 | B2: Abbott Laboratories | C2: 200011898 | D2: 10 | E2: KTC Building, plot 76,First Sector, City Center, Fifth Settlement, New Cairo, Cairo, Egypt. | F2: ehab.abdelaziz@abbott.com www.abbott.com | G2: Ehab Abdelaziz Senior Accountant
A3: C0002 | B3: Sovalue | D3: 10
A4: C0003 | B4: MICROSOFT EGYPT LLC | C4: 200143573 | D4: 10 | F4: v-lelhadidy@microsoft.com | G4: Lina El-Hadidy Marketing Coordinator – Integrated Marketing MEA Marketing Service Desk
A5: C0006 | B5: Cisco Systems Egypt Ltd. | C5: 200190423 | D5: 10 | E5: City Stars Project - Tower 2 A Omar Ibn El Khattab St. - Nasr City Cairo 11771 Egypt | F5: +20-1223120009 | G5: Accounts Payable | H5: kahedaya@cisco.com
A6: C0007 | B6: Ehab Hanna | D6: 10 | E6: Ehab13@msn.com | H6: Ehab13@msn.com
A7: C0008 | B7: Reconnaissance International | D7: 10 | E7: 1B The Beacon, Beaufront Park, Anick Road, Hexham, Northumberland, NE46 4TU, UK. | F7: +44 (0) 1932 508 807 | G7: Weronika Komorowska-Conference Manager | H7: weronika@recon-intl.com
A8: C0009 | B8: Dr. Ahmed Hendy So Value | D8: 10
A9: C0010 | B9: GV Developments | D9: 10 | E9: 62 South Taseen Stret Fifth Settlement, New Cairo, Cairo, Egypt.
A10: C0011 | B10: Elixir Pharma | D10: 10 | E10: Cairo, Sheraton Building , Heliopolis
A11: C0012 | B11: رفعت فتحى رمضان مرسى | D11: 10
A12: C0013 | B12: INTER CO MPANY FOR HOTEL TOURIS | D12: 10
A13: C0014 | B13: Mr. Maged Sami | D13: 10
A14: C0015 | B14: IQ Structures s.r.o. | D14: 10 | E14: Hlavní 130 250 68 Husinec-Řež Czech Republic | G14: Romana Čermáková Back Office Manager katerina.cerna@iqstructures.cz; ‎
A15: C0016 | B15: Giesecke+Devrient Currency Technology GmbH | D15: 10 | E15: Giesecke+Devrient Currency Technology GmbH Prinzregentenstr. 161, 81677 Munich, Germany www.gi-de.com/ct | F15: M +49-173 5430534 | G15: Michaela Reichert Head of Conferences and Events | H15: michaela.reichert@gi-de.com
A16: C0017 | B16: De La Rue | D16: 10 | E16: Langston Road, Loughton, Essex, IG10 3PB, United Kingdom | F16: +44 (0)20 8502 8019 or 8020 | fax: +44 (0)20 8502 1007 | G16: Maria Atkinson Government Relations Manager | H16: maria.atkinson@uk.delarue.com
A17: C0018 | B17: Landqart AG | D17: 10 | E17: Kantonsstrasse 16 | 7302 Landquart | Switzerland | F17: +41 81 307 92 49 | Fax: +41 81 307 91 43
A18: C0019 | B18: Meta Materials Inc (META®) | D18: 10 | E18: 60 Highfield Park Dr, Suite 102 Dartmouth, NS Canada B3A 4R9 | F18: 1-604-765-0593 | G18: Erin Jones Global Events Manager | H18: erin.jones@metamaterial.com
A19: C0020 | B19: Luminescene | D19: 10 | E19: The Fairway, Harlow, Essex, CM18 6NG, UK www.luminescence-scs.com | F19: T: +44 (0)1279 456400 | G19: Gerben van Wijk Sales and Marketing Director M: +44 (0)7506 118412 | H19: gerben.vanwijk@luminescence-scs.com
A20: C0021 | B20: JURA SECURITY PRINTING | D20: 10 | E20: Company (client): Jura JSP GmbH Address: A-1190 Vienna, Gebhardtgasse 13., Austria VAT number: ATU39169109 | F20: +36 1 275 1250 | G20: Éva Móritz eva.moritz@jura.hu | H20: eva.moritz@jura.hu
A21: C0022 | B21: Koenig & Bauer Banknote Solutions SA | D21: 10 | E21: Avenue du Grey 55, CH-1018 Lausanne PO Box 347, CH-1000 Lausanne 22 Switzerland | F21: +41 21 345 71 33 | G21: i.A. Vanessa Lauzier Marketing Communications vanessa.lauzier@koenig-bauer.com | H21: banknote-solutions.koenig-bauer.com
A22: C0023 | B22: Orell Füssli Ltd | D22: 10 | E22: Dietzingerstrasse 3 8036 Zurich, Switzerland | F22: +41444667422 | G22: Meri Torniainen Director Marketing and Communication | H22: meri.torniainen@orellfuessli.com
A23: C0024 | B23: Security Fibres UK African | D23: 10
A24: C0025 | B24: OBERTHUR FIDUCIAIRE | D24: 10 | E24: www.oberthur-fiduciaire.com | F24: +33 1 42 99 77 25 | G24: Charlotte Lafont Group Communications Manager | H24: c.lafont@fcof.com
A25: C0026 | B25: Crane Currency | D25: 10 | E25: 30 Main Street Dalton, Massachusetts USA | G25: Tod L Niedeck Marketing Director | H25: tod.niedeck@cranecurrency.com
A26: C0027 | B26: IMPRIMERIE NATIONALE SA | D26: 10 | E26: RUE DE FRERES BEAUMONT 59128 FLERS EN ESCREBIEUX France | F26: +33(0)1 64 76 31 00 | G26: Mehdi Benmebarek Secure Components BU Communications Manager | H26: mehdi.benmebarek@ingroupe.com
A27: C0028 | B27: LEONHARD KURZ Stiftung & Co. KG | D27: 10 | E27: Schwabacher Str. 482 90763 Fürth www.kurz.de | F27: +49 911 7141 9653 | G27: Michelle Carter Assistant & Project Coordinator Business Area Security - Banknotes | H27: michelle.carter@kurz.de
A28: C0029 | B28: Central Bank Of Egypt (banknote Printing Plant) The Association of African Banknotes and Security Document Printers. | D28: 10 | E28: 214 pyramids Road , Giza 12556 | F28: 20235990622 | G28: Eng. Mostafa Tobbala General Manager Procurement & Logistic Dept. | H28: mostafa.tobbala@cbe.org.eg
A29: C0030 | B29: Klayy Tech | D29: 10 | E29: Cairo, Smart Village, Building 19B www.klayytech.com | F29: Mobile: +2 01223651081 | G29: Mr.Sayed Mohamed ,MBA | Accounting Manager.
A30: C0031 | B30: E- Finance Co | C30: 616359772 | D30: 10 | E30: Smart Village, Building B 115, 2nd floor,KM 28 Cairo-Alex Desert Road, 12585 | G30: islam_elgamal@efinance.com.eg
A31: C0032 | B31: E- Finance Co 2 | C31: 215864379 | D31: 10 | E31: Smart Village, Building B 115, 2nd floor,KM 28 Cairo-Alex Desert Road, 12585 | G31: islam_elgamal@efinance.com.eg
A32: C0037 | B32: Orion 360 | C32: 340441933 | D32: 10
A33: C0038 | B33: US-AID | C33: 699058155 | D33: 10
A34: C0158 | B34: The Brand Mechanics | C34: 158 | D34: 10 | E34: 201,Al Ameri Tower Barsha Heights (tecom) Dubai , UAE | F34: +971 4 5541706 | G34: Jennifer Melecio
A35: C0159 | B35: Direct Egypt | C35: 200203495 | D35: 10
A36: C0160 | B36: VAS & IT VALLY | D36: 10
A37: C0165 | B37: EAST WEST ADVE RTISING(L.L.C) | D37: 10
A38: C0170 | B38: information Technology of Egypt Corporation | C38: 200122886 | D38: 10
A39: C0180 | B39: TEAMSTOK FZCO | D39: 10
A40: C0181 | B40: وليد طارق احمد موافي و شريكة | D40: 10
A41: C0202 | B41: Noventiq Egypt S.A.E for Information Technology | C41: 728382857 | D41: 10 | F41: +201117040840 | G41: Fatma Abdelsalam Regional Human Resources Manger MEA & Turkiye
A42: C0203 | B42: SILICON 21 | C42: 200016059 | D42: 10
A43: C0204 | B43: ETAX | C43: 618874704 | D43: 10 | E43: 104 ب 104 القريه الذكيه الكيلو 28 طريق مصر اسكندريه الصحراوي الجيزه 6 October City (1), Giza, EG
A44: C0205 | B44: Emma Horne Travel | D44: 10
A45: C0206 | B45: Eleveo a.s. | C45: 25730151 | D45: 10 | E45: Dock in Four - Block D Boudníkova 2514/7 180 00 Praha 8 – Libeň Czech Republic | F45: +420 222 554 111 | G45: Rebecca Rosas Global Marketing Director
A46: C0207 | B46: Imagicle DMCC | C46: 100333931200003 | D46: 10 | E46: Address Office 1305, JBCS, Cluster W. JTC, PO Box 283982,UAE | F46: M +971.555547337 | G46: Anas Assil Sales Manager ME
A47: C0208 | B47: VQ Communications Ltd | C47: 208 | D47: 10 | E47: Unit 4B, Byron House, Lansdowne Court, Bumpers Way, Chippenham SN14 6RZ, United Kingdom | F47: kburchell@vqcomms.com | G47: Katie Burchell
A48: C0209 | B48: Intercall Marketing Services Pte Ltd | D48: 10 | E48: 77 Science Park Drive, #03-15, Singapore 118256 | F48: 6598505038 | G48: Clarence Sim
A49: C0210 | B49: VAS Integrated Soluations | C49: 367287692 | D49: 10
A50: C0211 | B50: Kurmi Enterprise AE-ME & APAC I Kurmi Software | C50: 211 | D50: 10 | E50: Dubai,UAE | F50: +971(0)54 354 0555 | G50: Nabil Massri | H50: nabil.massri@kurmi-software.com

Sheet Own_Mtbl
A1: Own_ Code | B1: Own_Subled_Name | C1: Acc_Key | D1: Cost Center | E1: Exp Account Name
A2: Bnk_Cur | B2: Bnk_Curr | C2: 4 | D2: FinanceCost
A3: Bnk_Eur | B3: Bnk_Eur | C3: 5 | D3: FinanceCost
A4: Bnk_Sav | B4: Bnk_Sav | C4: 6 | D4: FinanceCost
A5: Bnk_Usd | B5: Bnk_Usd | C5: 7 | D5: FinanceCost
A6: Bnk_Trnz | B6: Bnk_Trnz | C6: 8 | D6: FinanceCost
A7: Bnk_Exp | B7: Bnk_Exp | C7: 39 | D7: FinanceCost
A8: MR. MAGED ATM | B8: MR. MAGED ATM | C8: 17 | D8: Mr.MagedPersonal
A9: Mr. MAGED SAMI | B9: Mr. MAGED SAMI | C9: 17 | D9: Mr.MagedPersonal
A10: Own001 | B10: ELEGANT EDUCATION HOME LYCEE | C10: 17 | D10: Mr.MagedPersonal | E10: Owner Current Account
A11: Own002 | B11: SHERINE ERNEST TAKLA GHOBRANY | C11: 17 | D11: Mr.MagedPersonal | E11: Owner Current Account
A12: Own003 | B12: AMIR EZZAT NESSIM AMIR NESSIM | C12: 17 | D12: Mr.MagedPersonal | E12: Owner Current Account
A13: Own004 | B13: MAGED SAMI SAWIRES- General Manager | C13: 17 | D13: Mr.MagedPersonal | E13: Owner Current Account
A14: Own005 | B14: CIB VIA CARD MR. Maged | C14: 17 | D14: Mr.MagedPersonal | E14: Owner Current Account
A15: Own006 | B15: NBE Mr. Maged Personal Account | C15: 17 | D15: Mr.MagedPersonal | E15: Owner Current Account
A16: Own007 | B16: Zo Clinicst CAI | C16: 17 | D16: Mr.MagedPersonal | E16: Owner Current Account
A17: Own008 | B17: Zo Clinic | C17: 17 | D17: Mr.MagedPersonal | E17: Owner Current Account
A18: Own009 | B18: UROPIAN CO FOR TOUR | C18: 17 | D18: Mr.MagedPersonal | E18: Owner Current Account
A19: Own010 | B19: UROPIAN CO FOR | C19: 17 | D19: Mr.MagedPersonal | E19: Owner Current Account
A20: Own011 | B20: U BISTRO REST C | C20: 17 | D20: Mr.MagedPersonal | E20: Owner Current Account
A21: Own012 | B21: U Bistro CAIRO | C21: 17 | D21: Mr.MagedPersonal | E21: Owner Current Account
... A132: Own123 | B132: La Via En Rose | C132: 17 | D132: Mr.MagedPersonal | E132: Owner Current Account

Sheet Stff_Mtbl
A1: Stf_ Code | B1: Stff_Subled_Name | C1: Cost Center | D1: Acc_Key | E1: AP -Account Name | F1: Exp Account Name
A2: Stf-0001 | B2: REHAM HISHAM RAMADAN HASSAN - Operation Manger | C2: Apply | D2: 11 | E2: Staff Payables | F2: Indirect Salary
A3: Stf-0002 | B3: EMAD HAMZA AHMED | C3: Apply | D3: 11 | E3: Staff Payables | F3: Indirect Salary
A4: Stf-0003 | B4: RANIA ADNAN AYESH SABAWI - Marketing Manager | C4: Apply | D4: 11 | E4: Staff Payables | F4: Indirect Salary
A5: Stf-0004 | B5: Ahmed Salah Gawish - Finance Controllar | C5: Apply | D5: 11 | E5: Staff Payables | F5: Indirect Salary
A6: Stf-0005 | B6: Eng. Khalied Tawheid | C6: IT & Computer Devises Lap tops | D6: 11 | E6: Staff Payables | F6: Indirect Salary
A7: Stf-0006 | B7: Lina Guide | C7: Apply | D7: 11 | E7: Staff Payables | F7: Indirect Salary
A8: Stf-0007 | B8: Nourhan | C8: Apply | D8: 11 | E8: Staff Payables | F8: Indirect Salary
A9: Stf-0008 | B9: Mahmoud EL Kanja | C9: Apply | D9: 11 | E9: Staff Payables | F9: Indirect Salary
A10: Stf-0009 | B10: Amany Nabil guide | C10: Apply | D10: 11 | E10: Staff Payables | F10: Indirect Salary
A11: Stf-0010 | B11: Leqaa Mohamed ING | C11: Apply | D11: 11 | E11: Staff Payables | F11: Indirect Salary

Sheet Einv_TrxMtbl
A1: Einv_Elc_Id | B1: التوجية المحاسبي | C1: Acc_Key | D1: رقم الأقرار الضريبي أ-خالد | E1: رقم الأقرار الضريبي2 | F1: مركز التكلفة
A2: 02YZX5QDS0H7M5TE21BWE0RG10 | B2: ح / مصاريف التأسيس وما قبل التشغيل | C2: =VLOOKUP(Inv_Master[[#This Row],[التوجية المحاسبي]],'COA_Mtble'!C:D,2,0) -> 1 | D2: ما قبل نوفمبر 2023 | E2: ما قبل نوفمبر 2023 | F2: 39
A3: 03XXTNPM3AZQSP26ANZW5ZPJ10 | B3: أيرادات التشغيل المباشر | C3: =VLOOKUP(Inv_Master[[#This Row],[التوجية المحاسبي]],'COA_Mtble'!C:D,2,0) -> 18 | D3: مارس@ 2025 | E3: مارس@ 2025 | F3: 105
A4: 03YQT0FNBWCKVEVGN1JYTZ3K10 | C4: =VLOOKUP(Inv_Master[[#This Row],[التوجية المحاسبي]],'COA_Mtble'!C:D,2,0) -> #N/A | F4: 115
A5: 09RND2X0P2PF6SK0HQ1S9D6K10 | C5: =VLOOKUP(Inv_Master[[#This Row],[التوجية المحاسبي]],'COA_Mtble'!C:D,2,0) -> #N/A | F5: N/A Admin Expn
A6: 0AP9TAE40B302RG6WXWFM9RH10 | B6: تكاليف تشغيل مباشر - أقامات فندية وحجز قاعات | C6: =VLOOKUP(Inv_Master[[#This Row],[التوجية المحاسبي]],'COA_Mtble'!C:D,2,0) -> 22 | D6: أقرار ديسمبر 2024 معدل | E6: مارس @2024 | F6: 79
A7: 0D0M6NB34AH8V57G1RHYG64J10 | B7: تكاليف تشغيل مباشر - دعاية وأعلان أعمال ديكور وأكشاك عرض | C7: =VLOOKUP(Inv_Master[[#This Row],[التوجية المحاسبي]],'COA_Mtble'!C:D,2,0) -> 24 | D7: أقرار ديسمبر 2024 معدل | E7: أغسطس @2024 | F7: 84
A8: 0NPTRHP8E0CH8K5EK3J1MDTJ10 | B8: تكاليف تشغيل مباشر - أنتقالات داخلية | C8: =VLOOKUP(Inv_Master[[#This Row],[التوجية المحاسبي]],'COA_Mtble'!C:D,2,0) -> 20 | D8: مايو @2025 | E8: مايو @2025 | F8: 108
A9: 0PHJAWFGA339N85D0RR9QXSJ10 | B9: تكاليف تشغيل مباشر - تذاكر طيران | C9: =VLOOKUP(Inv_Master[[#This Row],[التوجية المحاسبي]],'COA_Mtble'!C:D,2,0) -> 23 | D9: أبريل @ 2025 | E9: أبريل @ 2025 | F9: 108
A10: 0RB6D37SJ4Y85SWD6A43Y30J10 | B10: تكاليف تشغيل مباشر - أقامات فندية وحجز قاعات | C10: =VLOOKUP(Inv_Master[[#This Row],[التوجية المحاسبي]],'COA_Mtble'!C:D,2,0) -> 22 | D10: أقرار ديسمبر 2024 معدل | E10: يونيو@2024 | F10: 82
A11: 0RR9FMS6B061CAWBQW3V79EJ10 | B11: تكاليف تشغيل مباشر - دعاية وأعلان أعمال ديكور وأكشاك عرض | C11: =VLOOKUP(Inv_Master[[#This Row],[التوجية المحاسبي]],'COA_Mtble'!C:D,2,0) -> 24 | D11: أقرار ديسمبر 2024 معدل | E11: ديسمبر@2024 | F11: 88
A12: 0WJYY6Z5F4X1A8XH8NKE4PMH10 | B12: أيرادات التشغيل المباشر | C12: =VLOOKUP(Inv_Master[[#This Row],[التوجية المحاسبي]],'COA_Mtble'!C:D,2,0) -> 18 | D12: أقرار ديسمبر 2024 معدل | E12: يناير @2024 | F12: 76
A13: 0XE20G1RMFHSP69MWWH1R7ZJ10 | B13: تكاليف تشغيل مباشر - دعاية وأعلان مطبوعات | C13: =VLOOKUP(Inv_Master[[#This Row],[التوجية المحاسبي]],'COA_Mtble'!C:D,2,0) -> 25 | D13: يوليو@2025 | E13: يوليو@2025 | F13: 107
A14: 14F4000482WM19JZ25KNGYMJ10 | B14: تكاليف تشغيل مباشر - أغذية ومشروبات | C14: =VLOOKUP(Inv_Master[[#This Row],[التوجية المحاسبي]],'COA_Mtble'!C:D,2,0) -> 21 | D14: فبراير @ 2025 | E14: فبراير @ 2025 | F14: 103
A15: 19KNXMQYN3HDJNH0ZG9DHHRH10 | B15: تكاليف تشغيل مباشر - أقامات فندية وحجز قاعات | C15: =VLOOKUP(Inv_Master[[#This Row],[التوجية المحاسبي]],'COA_Mtble'!C:D,2,0) -> 22 | D15: أقرار ديسمبر 2024 معدل | E15: مارس @2024 | F15: 81
A16: 1BDH75FHEW8ZVK6X8FWD7Q9H10 | B16: Canclled | C16: Canclled | D16: ما قبل نوفمبر 2023 | E16: ما قبل نوفمبر 2023 | F16: N/A Admin Expn
A17: 1GSFJ01TXK61NG61CZHNCB2J10 | B17: أيرادات التشغيل المباشر | C17: =VLOOKUP(Inv_Master[[#This Row],[التوجية المحاسبي]],'COA_Mtble'!C:D,2,0) -> 18 | D17: يوليو@2024 | E17: يوليو@2024 | F17: 84
A18: 1JNCGKMB1YKM4PS0SX5FD8FG10 | B18: ح / مصاريف التأسيس وما قبل التشغيل | C18: =VLOOKUP(Inv_Master[[#This Row],[التوجية المحاسبي]],'COA_Mtble'!C:D,2,0) -> 1 | D18: ما قبل نوفمبر 2023 | E18: ما قبل نوفمبر 2023 | F18: 2
A19: 1MZ9KQ2DQTZYY257QW2Y3NWH10 | B19: تكاليف تشغيل مباشر - أنتقالات داخلية | C19: =VLOOKUP(Inv_Master[[#This Row],[التوجية المحاسبي]],'COA_Mtble'!C:D,2,0) -> 20 | D19: أقرار ديسمبر 2024 معدل | E19: أبريل@2024 | F19: 82
A20: 1N3WZG7KPA784HY4864YA5RH10 | B20: أيرادات التشغيل المباشر | C20: =VLOOKUP(Inv_Master[[#This Row],[التوجية المحاسبي]],'COA_Mtble'!C:D,2,0) -> 18 | D20: أقرار ديسمبر 2024 معدل | E20: مارس @2024 | F20: 79
A21: 1Y0W47Z445PCDQ4VJ3W63EGH10 | B21: مصروفات أدارية وعمومية - تكنولوجيا المعلومات و أدوات مكتبية | C21: =VLOOKUP(Inv_Master[[#This Row],[التوجية المحاسبي]],'COA_Mtble'!C:D,2,0) -> 32 | D21: نوفمبر@2023 | E21: نوفمبر@2023 | F21: N/A Admin Expn
A22: 21VC5FZADWGKY30PFQ95T3TJ10 | B22: تكاليف تشغيل مباشر - أنتقالات داخلية | C22: =VLOOKUP(Inv_Master[[#This Row],[التوجية المحاسبي]],'COA_Mtble'!C:D,2,0) -> 20 | D22: أبريل @ 2025 | E22: أبريل @ 2025 | F22: 108
A23: 26VQK4FVS6BFAW8S5FAKM1SJ10 | B23: تكاليف تشغيل مباشر - تذاكر طيران | C23: =VLOOKUP(Inv_Master[[#This Row],[التوجية المحاسبي]],'COA_Mtble'!C:D,2,0) -> 23 | D23: أبريل @ 2025 | E23: أبريل @ 2025 | F23: Mr.MagedPersonal
A24: 2C3ABMN90AE7DFS43NXM7XMH10 | B24: مصروفات أدارية وعمومية - تكنولوجيا المعلومات و أدوات مكتبية | C24: =VLOOKUP(Inv_Master[[#This Row],[التوجية المحاسبي]],'COA_Mtble'!C:D,2,0) -> 32 | D24: أقرار ديسمبر 2024 معدل | E24: يناير @2024 | F24: N/A Admin Expn
A25: 2C8XES2YM0YQZPACZYAN27SJ10 | B25: تكاليف تشغيل مباشر - أغذية ومشروبات | C25: =VLOOKUP(Inv_Master[[#This Row],[التوجية المحاسبي]],'COA_Mtble'!C:D,2,0) -> 21 | D25: أبريل @ 2025 | E25: أبريل @ 2025 | F25: 110
A26: 2DX6HT44M15C0BBV33VMACBJ10 | B26: مصروفات أدارية وعمومية - تكنولوجيا المعلومات و أدوات مكتبية | C26: =VLOOKUP(Inv_Master[[#This Row],[التوجية المحاسبي]],'COA_Mtble'!C:D,2,0) -> 32 | D26: أقرار ديسمبر 2024 معدل | E26: أكتوبر@2024 | F26: N/A Admin Expn
A27: 2GE0XBFZ7M4A19KQ8T2J9TZJ10 | B27: تكاليف تشغيل مباشر - دعاية وأعلان أعمال ديكور وأكشاك عرض | C27: =VLOOKUP(Inv_Master[[#This Row],[التوجية المحاسبي]],'COA_Mtble'!C:D,2,0) -> 24 | D27: يوليو@2025 | E27: يوليو@2025 | F27: 113
A28: 2NE02KB5WMJ0AMMM49EQ3A6K10 | C28: =VLOOKUP(Inv_Master[[#This Row],[التوجية المحاسبي]],'COA_Mtble'!C:D,2,0) -> #N/A | F28: 115
A29: 2RQ0XG5SGDMRY3VG89TSE3JH10 | B29: تكاليف تشغيل مباشر - أقامات فندية وحجز قاعات | C29: =VLOOKUP(Inv_Master[[#This Row],[التوجية المحاسبي]],'COA_Mtble'!C:D,2,0) -> 22 | D29: ديسمبر@2023 | E29: ديسمبر@2023 | F29: 72
A30: 2S5E44XDV4YJKD8VQ7J3HVSJ10 | B30: تكاليف تشغيل مباشر - دعاية وأعلان أعمال ديكور وأكشاك عرض | C30: =VLOOKUP(Inv_Master[[#This Row],[التوجية المحاسبي]],'COA_Mtble'!C:D,2,0) -> 24 | D30: أبريل @ 2025 | E30: أبريل @ 2025 | F30: 109
A31: 2WPKX9CDVBPS1X2H2VXTXV1J10 | B31: أيرادات التشغيل المباشر | C31: =VLOOKUP(Inv_Master[[#This Row],[التوجية المحاسبي]],'COA_Mtble'!C:D,2,0) -> 18 | D31: يوليو@2024 | E31: يوليو@2024 | F31: 84
A32: 32NGZ3R77W695NM3751425VJ10 | B32: تكاليف تشغيل مباشر - تذاكر طيران | C32: =VLOOKUP(Inv_Master[[#This Row],[التوجية المحاسبي]],'COA_Mtble'!C:D,2,0) -> 23 | D32: مايو @2025 | E32: مايو @2025 | F32: 108
A33: 33VPZH7A3TPHFGGZDCQHZZ5K10 | C33: =VLOOKUP(Inv_Master[[#This Row],[التوجية المحاسبي]],'COA_Mtble'!C:D,2,0) -> #N/A | F33: 119
A34: 34NGJN6GTE4E6RM8PEVYSEGJ10 | B34: مصروفات أدارية وعمومية - تكنولوجيا المعلومات و أدوات مكتبية | C34: =VLOOKUP(Inv_Master[[#This Row],[التوجية المحاسبي]],'COA_Mtble'!C:D,2,0) -> 32 | D34: أقرار ديسمبر 2024 معدل | E34: ديسمبر@2024 | F34: Mercedes-Benz - Assets 592.ق.ط.ب
A35: 34QV2AQ3VGM95FGYR1QBB8QH10 | B35: تكاليف تشغيل مباشر - دعاية وأعلان تصوير وتوثيق الفعليات | C35: =VLOOKUP(Inv_Master[[#This Row],[التوجية المحاسبي]],'COA_Mtble'!C:D,2,0) -> 26 | D35: أقرار ديسمبر 2024 معدل | E35: فبراير@2024 | F35: 78
A36: 389SWW7TQ0PXD057QEZR1Q6K10 | C36: =VLOOKUP(Inv_Master[[#This Row],[التوجية المحاسبي]],'COA_Mtble'!C:D,2,0) -> #N/A | F36: 115
A37: 390AM81A1GQQ7EC2MB8JNW8J10 | B37: تكاليف تشغيل مباشر - دعاية وأعلان تأجير شاشات عرض ومؤثرات صوتية ومعدات إضاءة | C37: =VLOOKUP(Inv_Master[[#This Row],[التوجية المحاسبي]],'COA_Mtble'!C:D,2,0) -> 29 | D37: أقرار ديسمبر 2024 معدل | E37: سبتمبر@2024 | F37: 85
A38: 3K5K62V9NB41ZQ2XMHT22HKJ10 | B38: تكاليف تشغيل مباشر - دعاية وأعلان مطبوعات | C38: =VLOOKUP(Inv_Master[[#This Row],[التوجية المحاسبي]],'COA_Mtble'!C:D,2,0) -> 25 | D38: فبراير @ 2025 | E38: فبراير @ 2025 | F38: 103
A39: 3N4ZTDH7B51MF6BVCT6F6HPH10 | B39: أيرادات التشغيل المباشر | C39: =VLOOKUP(Inv_Master[[#This Row],[التوجية المحاسبي]],'COA_Mtble'!C:D,2,0) -> 18 | D39: فبراير@2024 | E39: فبراير@2024 | F39: 71
A40: 3NX66PMN1D1GXCFSMAQN1E6K10 | C40: =VLOOKUP(Inv_Master[[#This Row],[التوجية المحاسبي]],'COA_Mtble'!C:D,2,0) -> #N/A | F40: 115
A41: 3QC841RAQQMVS20Q5C4K7SRH10 | B41: أيرادات التشغيل المباشر | C41: =VLOOKUP(Inv_Master[[#This Row],[التوجية المحاسبي]],'COA_Mtble'!C:D,2,0) -> 18 | D41: أقرار ديسمبر 2024 معدل | E41: مارس @2024 | F41: 79
A42: 3SX4HP14H8193TNXJ1H069FH10 | B42: أيرادات التشغيل المباشر | C42: =VLOOKUP(Inv_Master[[#This Row],[التوجية المحاسبي]],'COA_Mtble'!C:D,2,0) -> 18 | D42: نوفمبر@2023 | E42: نوفمبر@2023 | F42: 74
A43: 3XMQYR30BG7VXAJVZX8QHH8J10 | B43: Cancelled | C43: Canclled | D43: سبتمبر@2024 | E43: سبتمبر@2024 | F43: N/A Admin Expn
A44: 43SAH0DR86BRKW1BGP9633VG10 | B44: ح / مصاريف التأسيس وما قبل التشغيل | C44: =VLOOKUP(Inv_Master[[#This Row],[التوجية المحاسبي]],'COA_Mtble'!C:D,2,0) -> 1 | D44: ما قبل نوفمبر 2023 | E44: ما قبل نوفمبر 2023 | F44: 65
A45: 489KB8HQ15XRDNBZFFGCQ4VJ10 | B45: مصروفات أدارية وعمومية - تكنولوجيا المعلومات و أدوات مكتبية | C45: =VLOOKUP(Inv_Master[[#This Row],[التوجية المحاسبي]],'COA_Mtble'!C:D,2,0) -> 32 | D45: مايو @2025 | E45: مايو @2025 | F45: 108
A46: 4F1JT1HG9KQ2Y5MGNQ3WQMXJ10 | B46: تكاليف تشغيل مباشر - دعاية وأعلان مطبوعات | C46: =VLOOKUP(Inv_Master[[#This Row],[التوجية المحاسبي]],'COA_Mtble'!C:D,2,0) -> 25 | D46: يونيو@2025 | E46: يونيو@2025 | F46: 102
A47: 4FMRD61S24BFY5KZ1G0V558H10 | B47: تكاليف تشغيل مباشر - دعاية وأعلان تصوير وتوثيق الفعليات | C47: =VLOOKUP(Inv_Master[[#This Row],[التوجية المحاسبي]],'COA_Mtble'!C:D,2,0) -> 26 | D47: ما قبل نوفمبر 2023 | E47: ما قبل نوفمبر 2023 | F47: 2
A48: 4HHCSR9PTQV3DGRSVZQ0808J10 | B48: تكاليف تشغيل مباشر - أنتقالات داخلية | C48: =VLOOKUP(Inv_Master[[#This Row],[التوجية المحاسبي]],'COA_Mtble'!C:D,2,0) -> 20 | D48: أقرار ديسمبر 2024 معدل | E48: سبتمبر@2024 | F48: 84
A49: 4JFWDBXNQBNYMMHKCBFYKTBH10 | B49: تكاليف تشغيل مباشر - أقامات فندية وحجز قاعات | C49: =VLOOKUP(Inv_Master[[#This Row],[التوجية المحاسبي]],'COA_Mtble'!C:D,2,0) -> 22 | D49: ما قبل نوفمبر 2023 | E49: ما قبل نوفمبر 2023 | F49: 70
A50: 4KED550STPYVAJPCG8407ZPJ10 | B50: أيرادات التشغيل المباشر | C50: =VLOOKUP(Inv_Master[[#This Row],[التوجية المحاسبي]],'COA_Mtble'!C:D,2,0) -> 18 | D50: مارس@ 2025 | E50: مارس@ 2025 | F50: 106
A51: 4QEH7F59BZXJ0X936VEK77DJ10 | B51: تكاليف تشغيل مباشر - دعاية وأعلان أعمال ديكور وأكشاك عرض | C51: =VLOOKUP(Inv_Master[[#This Row],[التوجية المحاسبي]],'COA_Mtble'!C:D,2,0) -> 24 | D51: أقرار ديسمبر 2024 معدل | E51: نوفمبر@2024 | F51: 85
A52: 4SV42RPADWWQMFEQSRBFJFTJ10 | B52: تكاليف تشغيل مباشر - دعاية وأعلان أعمال ديكور وأكشاك عرض | C52: =VLOOKUP(Inv_Master[[#This Row],[التوجية المحاسبي]],'COA_Mtble'!C:D,2,0) -> 24 | D52: أبريل @ 2025 | E52: أبريل @ 2025 | F52: 107
A53: 4TG9NJN4CDNBZG6QTQKNGGGH10 | B53: أيرادات التشغيل المباشر | C53: =VLOOKUP(Inv_Master[[#This Row],[التوجية المحاسبي]],'COA_Mtble'!C:D,2,0) -> 18 | D53: نوفمبر@2023 | E53: نوفمبر@2023 | F53: 74
A54: 4V4RC9SDP3N9RENZ0TY2ACBJ10 | B54: تكاليف تشغيل مباشر - أنتقالات داخلية | C54: =VLOOKUP(Inv_Master[[#This Row],[التوجية المحاسبي]],'COA_Mtble'!C:D,2,0) -> 20 | D54: أقرار ديسمبر 2024 معدل | E54: أكتوبر@2024 | F54: 87
A55: 4W8S9MTEYD90Z7KK911EEFXJ10 | B55: أيرادات التشغيل المباشر | C55: =VLOOKUP(Inv_Master[[#This Row],[التوجية المحاسبي]],'COA_Mtble'!C:D,2,0) -> 18 | D55: يونيو@2025 | E55: يونيو@2025 | F55: 113
... A58: 4Z0WMS5Y604JTT73MBXRH87H10 | B58: تكاليف تشغيل مباشر - أغذية ومشروبات | C58: =VLOOKUP(Inv_Master[[#This Row],[التوجية المحاسبي]],'COA_Mtble'!C:D,2,0) -> 21 | D58: ما قبل نوفمبر 2023 | E58: ما قبل نوفمبر 2023 | F58: 69
A59: 4ZYHZVWWMVXRKTC10CYMXN5K10 | C59: =VLOOKUP(Inv_Master[[#This Row],[التوجية المحاسبي]],'COA_Mtble'!C:D,2,0) -> #N/A | F59: 120
A60: 56STAK6H60WT3GS86HX9T3TJ10 | B60: تكاليف تشغيل مباشر - أنتقالات داخلية | C60: =VLOOKUP(Inv_Master[[#This Row],[التوجية المحاسبي]],'COA_Mtble'!C:D,2,0) -> 20 | D60: أبريل @ 2025 | E60: أبريل @ 2025 | F60: 108
A61: 5AW2VT6R7XT36NNNQQGQCMNG10 | B61: ح / مصاريف التأسيس وما قبل التشغيل | C61: =VLOOKUP(Inv_Master[[#This Row],[التوجية المحاسبي]],'COA_Mtble'!C:D,2,0) -> 1 | D61: ما قبل نوفمبر 2023 | E61: ما قبل نوفمبر 2023 | F61: N/A Admin Expn
A62: 5B79ZP6YT7R23SZADNH30FMJ10 | B62: مصروفات أدارية وعمومية - تكنولوجيا المعلومات و أدوات مكتبية | C62: =VLOOKUP(Inv_Master[[#This Row],[التوجية المحاسبي]],'COA_Mtble'!C:D,2,0) -> 32 | D62: فبراير @ 2025 | E62: فبراير @ 2025 | F62: 102
A63: 5H7G22FBF90Y8DQ106SM8ANH10 | B63: أيرادات التشغيل المباشر | C63: =VLOOKUP(Inv_Master[[#This Row],[التوجية المحاسبي]],'COA_Mtble'!C:D,2,0) -> 18 | D63: أقرار ديسمبر 2024 معدل | E63: يناير @2024 | F63: 77
A64: 5H9VNXH8V5W2AA13VG2ASDGH10 | B64: تكاليف تشغيل مباشر - دعاية وأعلان تأجير شاشات عرض ومؤثرات صوتية ومعدات إضاءة | C64: =VLOOKUP(Inv_Master[[#This Row],[التوجية المحاسبي]],'COA_Mtble'!C:D,2,0) -> 29 | D64: نوفمبر@2023 | E64: نوفمبر@2023 | F64: 72
A65: 5QWDKBHBGAC10W3H5WA2SZTJ10 | B65: تكاليف تشغيل مباشر - أقامات فندية وحجز قاعات | C65: =VLOOKUP(Inv_Master[[#This Row],[التوجية المحاسبي]],'COA_Mtble'!C:D,2,0) -> 22 | D65: مايو @2025 | E65: مايو @2025 | F65: 108
A66: 5R3AYPVPRZZ9FFXRR8JS2XZJ10 | B66: مصروفات أدارية وعمومية - مصروفات وقود وصيانة سيارة تأمين سيارة | C66: =VLOOKUP(Inv_Master[[#This Row],[التوجية المحاسبي]],'COA_Mtble'!C:D,2,0) -> 38 | D66: يوليو@2025 | E66: يوليو@2025 | F66: Mercedes-Benz - Assets 592.ق.ط.ب
A67: 5ZMWMTARFVX0Q3F3QV7YKDTJ10 | B67: تكاليف تشغيل مباشر - أنتقالات داخلية | C67: =VLOOKUP(Inv_Master[[#This Row],[التوجية المحاسبي]],'COA_Mtble'!C:D,2,0) -> 20 | D67: مايو @2025 | E67: مايو @2025 | F67: 108
A68: 5ZSNCV0KJYHMHCP0BHW6995K10 | C68: =VLOOKUP(Inv_Master[[#This Row],[التوجية المحاسبي]],'COA_Mtble'!C:D,2,0) -> #N/A | F68: N/A Admin Expn
A69: 60YGSXEXRWP5XDWKSB90P2QH10 | B69: تكاليف تشغيل مباشر - دعاية وأعلان تصوير وتوثيق الفعليات | C69: =VLOOKUP(Inv_Master[[#This Row],[التوجية المحاسبي]],'COA_Mtble'!C:D,2,0) -> 26 | D69: فبراير@2024 | E69: فبراير@2024 | F69: 78
A70: 639AD2SGGXT45RKVSYKSNJQH10 | B70: مصروفات أدارية وعمومية - تكنولوجيا المعلومات و أدوات مكتبية | C70: =VLOOKUP(Inv_Master[[#This Row],[التوجية المحاسبي]],'COA_Mtble'!C:D,2,0) -> 32 | D70: أقرار ديسمبر 2024 معدل | E70: فبراير@2024 | F70: 79
A71: 660K5SNH3AXS386N4T0TCMNG10 | B71: ح / مصاريف التأسيس وما قبل التشغيل | C71: =VLOOKUP(Inv_Master[[#This Row],[التوجية المحاسبي]],'COA_Mtble'!C:D,2,0) -> 1 | D71: ما قبل نوفمبر 2023 | E71: ما قبل نوفمبر 2023 | F71: N/A Admin Expn
A72: 6A2399Z2QYH11WCJECXV5W4K10 | C72: =VLOOKUP(Inv_Master[[#This Row],[التوجية المحاسبي]],'COA_Mtble'!C:D,2,0) -> #N/A | F72: 116
A73: 6CAM69BFC9JR19ZNTJXPCB5K10 | C73: =VLOOKUP(Inv_Master[[#This Row],[التوجية المحاسبي]],'COA_Mtble'!C:D,2,0) -> #N/A | F73: 115
A74: 6E4DRXQ5JD8HV3RT43GR3ZQH10 | B74: تكاليف تشغيل مباشر - أغذية ومشروبات | C74: =VLOOKUP(Inv_Master[[#This Row],[التوجية المحاسبي]],'COA_Mtble'!C:D,2,0) -> 21 | D74: أقرار ديسمبر 2024 معدل | E74: مارس @2024 | F74: 79
A75: 6FTKBK85HR8MYV1YPJYRZBWJ10 | B75: تكاليف تشغيل مباشر - أغذية ومشروبات | C75: =VLOOKUP(Inv_Master[[#This Row],[التوجية المحاسبي]],'COA_Mtble'!C:D,2,0) -> 21 | D75: يونيو@2025 | E75: يونيو@2025 | F75: 112
A76: 6H7R5RW5AZKBK5WZMF3Y7A6K10 | C76: =VLOOKUP(Inv_Master[[#This Row],[التوجية المحاسبي]],'COA_Mtble'!C:D,2,0) -> #N/A | F76: 115
A77: 6JBZFHM50TPHK20TFZN0JHDJ10 | B77: تكاليف تشغيل مباشر - دعاية وأعلان مطبوعات | C77: =VLOOKUP(Inv_Master[[#This Row],[التوجية المحاسبي]],'COA_Mtble'!C:D,2,0) -> 25 | D77: أقرار ديسمبر 2024 معدل | E77: نوفمبر@2024 | F77: 94
A78: 6RAQJZCZX2GB1GKQ4MWVD9BJ10 | B78: أيرادات التشغيل المباشر | C78: =VLOOKUP(Inv_Master[[#This Row],[التوجية المحاسبي]],'COA_Mtble'!C:D,2,0) -> 18 | D78: أكتوبر@2024 | E78: أكتوبر@2024 | F78: 87
A79: 6SGTR5GDND48XQ7X3BBX0VEJ10 | B79: تكاليف تشغيل مباشر - أقامات فندية وحجز قاعات | C79: =VLOOKUP(Inv_Master[[#This Row],[التوجية المحاسبي]],'COA_Mtble'!C:D,2,0) -> 22 | D79: أقرار ديسمبر 2024 معدل | E79: ديسمبر@2024 | F79: 91
A80: 6W99TJ471SAFWEHCAV28S7SJ10 | B80: أيرادات التشغيل المباشر | C80: =VLOOKUP(Inv_Master[[#This Row],[التوجية المحاسبي]],'COA_Mtble'!C:D,2,0) -> 18 | D80: أبريل @ 2025 | E80: أبريل @ 2025 | F80: 109
A81: 71RS5J248S9CA7VZ9KQQZZ5K10 | C81: =VLOOKUP(Inv_Master[[#This Row],[التوجية المحاسبي]],'COA_Mtble'!C:D,2,0) -> #N/A | F81: 115
A82: 72PNMJN53C0VSJATJKWBDNEJ10 | B82: تكاليف تشغيل مباشر - أقامات فندية وحجز قاعات | C82: =VLOOKUP(Inv_Master[[#This Row],[التوجية المحاسبي]],'COA_Mtble'!C:D,2,0) -> 22 | D82: أقرار ديسمبر 2024 معدل | E82: ديسمبر@2024 | F82: 88
A83: 74F78E7PX60YRFCV0W3CJTBH10 | B83: تكاليف تشغيل مباشر - أقامات فندية وحجز قاعات | C83: =VLOOKUP(Inv_Master[[#This Row],[التوجية المحاسبي]],'COA_Mtble'!C:D,2,0) -> 22 | D83: ما قبل نوفمبر 2023 | E83: ما قبل نوفمبر 2023 | F83: 70
A84: 76YQRM96WQHHH45PF05ATCRJ10 | B84: تكاليف تشغيل مباشر - أنتقالات داخلية | C84: =VLOOKUP(Inv_Master[[#This Row],[التوجية المحاسبي]],'COA_Mtble'!C:D,2,0) -> 20 | D84: أبريل @ 2025 | E84: أبريل @ 2025 | F84: Mr.MagedPersonal
A85: 79EGQT0SN522VVKR6QCGZZ5K10 | C85: =VLOOKUP(Inv_Master[[#This Row],[التوجية المحاسبي]],'COA_Mtble'!C:D,2,0) -> #N/A | F85: 115
A86: 7BFN638TQA9H2PZTWGBFZBBJ10 | B86: أيرادات التشغيل المباشر | C86: =VLOOKUP(Inv_Master[[#This Row],[التوجية المحاسبي]],'COA_Mtble'!C:D,2,0) -> 18 | D86: يناير @ 2025 | E86: أكتوبر@2024 | F86: 87
A87: 7Z473CA4JYRK1R7EFXSS7G6K10 | C87: =VLOOKUP(Inv_Master[[#This Row],[التوجية المحاسبي]],'COA_Mtble'!C:D,2,0) -> #N/A | F87: 116
A88: 878JC7T854SGKMQQSYAN04NJ10 | B88: تكاليف تشغيل مباشر - أقامات فندية وحجز قاعات | C88: =VLOOKUP(Inv_Master[[#This Row],[التوجية المحاسبي]],'COA_Mtble'!C:D,2,0) -> 22 | D88: فبراير @ 2025 | E88: فبراير @ 2025 | F88: 103
A89: 88JM7S798CBF492CRMRXN2HJ10 | B89: مصروفات أدارية وعمومية - تكنولوجيا المعلومات و أدوات مكتبية | C89: =VLOOKUP(Inv_Master[[#This Row],[التوجية المحاسبي]],'COA_Mtble'!C:D,2,0) -> 32 | D89: يناير @ 2025 | E89: يناير @ 2025 | F89: 91
A90: 89PJRB3FXWX665HG7CGY386K10 | C90: =VLOOKUP(Inv_Master[[#This Row],[التوجية المحاسبي]],'COA_Mtble'!C:D,2,0) -> #N/A | F90: 117
A91: 8AMYDWE2FE03ZGDKNPAGXZYJ10 | B91: تكاليف تشغيل مباشر - دعاية وأعلان تأجير شاشات عرض ومؤثرات صوتية ومعدات إضاءة | C91: =VLOOKUP(Inv_Master[[#This Row],[التوجية المحاسبي]],'COA_Mtble'!C:D,2,0) -> 29 | D91: يونيو@2025 | E91: يونيو@2025 | F91: 113
A92: 8C9A7HV90EDWANABBDWTXVSJ10 | B92: تكاليف تشغيل مباشر - تذاكر طيران | C92: =VLOOKUP(Inv_Master[[#This Row],[التوجية المحاسبي]],'COA_Mtble'!C:D,2,0) -> 23 | D92: أبريل @ 2025 | E92: أبريل @ 2025 | F92: 108
A93: 8E5RZM77ERCARPW1QS4ZZD5K10 | C93: =VLOOKUP(Inv_Master[[#This Row],[التوجية المحاسبي]],'COA_Mtble'!C:D,2,0) -> #N/A | F93: 119
A94: 8FFRZZ0E9AJV8C4VVWRQ87BJ10 | B94: تكاليف تشغيل مباشر - أقامات فندية وحجز قاعات | C94: =VLOOKUP(Inv_Master[[#This Row],[التوجية المحاسبي]],'COA_Mtble'!C:D,2,0) -> 22 | D94: أقرار ديسمبر 2024 معدل | E94: أكتوبر@2024 | F94: 86
A95: 8K1VZH0A7XRF0T48RR644YSJ10 | B95: تكاليف تشغيل مباشر - دعاية وأعلان تأجير شاشات عرض ومؤثرات صوتية ومعدات إضاءة | C95: =VLOOKUP(Inv_Master[[#This Row],[التوجية المحاسبي]],'COA_Mtble'!C:D,2,0) -> 29 | D95: أبريل @ 2025 | E95: أبريل @ 2025 | F95: 108
A96: 8X6TNE25JKJC0ECE28TSW5QH10 | B96: تكاليف تشغيل مباشر - دعاية وأعلان أعمال ديكور وأكشاك عرض | C96: =VLOOKUP(Inv_Master[[#This Row],[التوجية المحاسبي]],'COA_Mtble'!C:D,2,0) -> 24 | D96: أقرار ديسمبر 2024 معدل | E96: فبراير@2024 | F96: 76
A97: 8Y58J1ZZ6AKCJ33JFFGCQ4VJ10 | B97: مصروفات أدارية وعمومية - تكنولوجيا المعلومات و أدوات مكتبية | C97: =VLOOKUP(Inv_Master[[#This Row],[التوجية المحاسبي]],'COA_Mtble'!C:D,2,0) -> 32 | D97: مايو @2025 | E97: مايو @2025 | F97: 108
A98: 99EV6NFNZYB9H05AWDEAR3WJ10 | B98: تكاليف تشغيل مباشر - تذاكر طيران | C98: =VLOOKUP(Inv_Master[[#This Row],[التوجية المحاسبي]],'COA_Mtble'!C:D,2,0) -> 23 | D98: مايو @2025 | E98: مايو @2025 | F98: Mr.MagedPersonal
A99: 9CD3A38JAEBN55ACZ3CSHH8J10 | B99: تكاليف تشغيل مباشر - دعاية وأعلان أعمال ديكور وأكشاك عرض | C99: =VLOOKUP(Inv_Master[[#This Row],[التوجية المحاسبي]],'COA_Mtble'!C:D,2,0) -> 24 | D99: أقرار ديسمبر 2024 معدل | E99: سبتمبر@2024 | F99: 86
A100: 9M98QXVRG3D98JA3YA4S695K10 | C100: =VLOOKUP(Inv_Master[[#This Row],[التوجية المحاسبي]],'COA_Mtble'!C:D,2,0) -> #N/A | F100: N/A Admin Expn
A101: 9RKDA2EYRQSNM6T29NASF95K10 | C101: =VLOOKUP(Inv_Master[[#This Row],[التوجية المحاسبي]],'COA_Mtble'!C:D,2,0) -> #N/A | F101: 119
A102: 9SHDMQPQ59VXCX6YDEDYTWYH10 | B102: تكاليف تشغيل مباشر - أغذية ومشروبات | C102: =VLOOKUP(Inv_Master[[#This Row],[التوجية المحاسبي]],'COA_Mtble'!C:D,2,0) -> 21 | D102: أقرار ديسمبر 2024 معدل | E102: مايو@2024 | F102: 83
...

Sheet Bud_Pur_Trxtbl
A1: PNR_ID | B1: Assigned to supplier | C1: Ven_ID | D1: Item Des. | E1: Units | F1: no of nightsn
A2: 04.25.C0003.110 | B2: ABU GHALI TUR | C2: V-0098 | D2: Car with driver at disposal for 8hrs (Mercedes E class - 2019) | E2: 1 | F2: 1
A3: 05.25.C0202.108 | B3: Momento Iman Thaha Naouf | C3: V-0061 | D3: *Gala Dinner Sound System Incl Stage system +sound system + light system+LED Screen | E3: 1 | F3: 1
A4: 05.25.C0202.108 | B4: Momento Iman Thaha Naouf | C4: V-0061 | D4: stage + 3*2 LED Screen
A5: 02.25.C0180.102 | B5: Ahmed Mahmoud Aly Mohamed Barakat Photo grapher | C5: V-0025 | D5: Photo Shooting | E5: 1 | F5: 1
A6: 02.25.C0180.102 | B6: Ahmed Mahmoud Aly Mohamed Barakat Photo grapher | C6: V-0025 | D6: Video Shooting | E6: 1 | F6: 1
A7: 02.25.C0180.102 | B7: Ahmed Mahmoud Aly Mohamed Barakat Photo grapher | C7: V-0025 | D7: Promo Movie : 2-3min movie for the whole event & main highlights with montage & effects | E7: 1 | F7: 1
A8: 02.25.C0180.102 | B8: Ahmed Mahmoud Aly Mohamed Barakat Photo grapher | C8: V-0025 | D8: Photo Printing - on spot | E8: 1 | F8: 1
A9: 03.25.C0003.105 | B9: Ahmed Mahmoud Aly Mohamed Barakat Photo grapher | C9: V-0025 | D9: Video Shooting | E9: 1 | F9: 1
A10: 03.25.C0003.105 | B10: Ahmed Mahmoud Aly Mohamed Barakat Photo grapher | C10: V-0025 | D10: Promo Movie : 2-3min movie for the whole event & main highlights with montage & effects | E10: 1 | F10: 1
A11: 03.25.C0003.105 | B11: Ahmed Mahmoud Aly Mohamed Barakat Photo grapher | C11: V-0025 | D11: Photo Shooting | E11: 1 | F11: 1
A12: 05.25.C0202.108 | B12: Ahmed Mahmoud Aly Mohamed Barakat Photo grapher | C12: V-0025 | D12: Daily Full photo & video shooting (throughout the whole day) - 2 shifts | E12: 1 | F12: 3
A13: 05.25.C0202.108 | B13: Ahmed Mahmoud Aly Mohamed Barakat Photo grapher | C13: V-0025 | D13: Promo Movie; 3-5min of the whole event with montage & effects | E13: 1 | F13: 1
A14: 04.25.C0003.109 | B14: Ahmed Mahmoud Aly Mohamed Barakat Photo grapher | C14: V-0025 | D14: Photo Shooting | E14: 1 | F14: 1
A15: 04.25.C0003.109 | B15: Ahmed Mahmoud Aly Mohamed Barakat Photo grapher | C15: V-0025 | D15: Video Shooting | E15: 1 | F15: 0
A16: 04.25.C0003.109 | B16: Ahmed Mahmoud Aly Mohamed Barakat Photo grapher | C16: V-0025 | D16: Promo Movie : 2-3min movie for the whole event & main highlights with montage & effects | E16: 1 | F16: 0
... A19: 04.25.C0003.110 | B19: Ariz | C19: V-0094 | D19: Catering - MS Office | E19: 1 | F19: 1
A20: 05.25.C0202.108 | B20: Aspire for Traning | C20: V-0092 | D20: Special Team Activity (combining wellness with physical activity & productivity)
A21: 04.25.C0003.109 | B21: B. Brand | C21: V-0091 | D21: 2 -Media Walla | E21: 1 | F21: 1
A22: 04.25.C0003.109 | B22: B. Brand | C22: V-0091 | D22: 4- Main screen Frame / Backdrop | E22: 1 | F22: 1
A23: 04.25.C0003.109 | B23: B. Brand | C23: V-0091 | D23: Poduim with logo & back lights
A24: 04.25.C0003.109 | B24: B. Brand | C24: V-0091 | D24: 1- Gate | E24: 1 | F24: 1
A25: 05.25.C0202.108 | B25: CAIRO Trade | C25: V-0088 | D25: ** Cooler Box 20 ltr | E25: 65 | F25: 1
A26: 04.25.C0003.109 | B26: CAIRO Trade | C26: V-0088 | D26: Option 1 Cooler box | E26: 8 | F26: 1
A27: 05.25.C0202.108 | B27: CARNIVAL SAMEH Egyptian Art for Show | C27: V-0087 | D27: Gala Dinner Entretainment Options : Trio
A28: 04.25.C0003.109 | B28: Comtech Egypt Audio Visual Event Management | C28: V-0027 | D28: 8m width X 2m depth X 0.4m height with stairs | E28: 1 | F28: 1
A29: 04.25.C0003.109 | B29: Comtech Egypt Audio Visual Event Management | C29: V-0027 | D29: on ground screens for presenters & speakers - in sync with the main screen | E29: 1 | F29: 1
A30: 04.25.C0003.109 | B30: Comtech Egypt Audio Visual Event Management | C30: V-0027 | D30: LED screen - for multi usage of presentation & as branding backdrop / P2 - 4m width X 3m height | E30: 12 | F30: 1
A31: 04.25.C0003.109 | B31: Comtech Egypt Audio Visual Event Management | C31: V-0027 | D31: 2 LED Towers (Each 3*1) | E31: 6 | F31: 1
A32: 04.25.C0003.109 | B32: Comtech Egypt Audio Visual Event Management | C32: V-0027 | D32: Basic Sound System - with 2 wireless mics | E32: 1 | F32: 1
A33: 04.25.C0003.109 | B33: Comtech Egypt Audio Visual Event Management | C33: V-0027 | D33: 3- LED Towers (each 1m width X 3m height) | E33: 2 | F33: 3
A34: 02.25.C0180.102 | B34: Comtech Egypt Audio Visual Event Management | C34: V-0027 | D34: 2 main LED screens on sides (each 4m width X 3m height) - totaling 24 meters screens | E34: 24 | F34: 1.5
A35: 02.25.C0180.102 | B35: Comtech Egypt Audio Visual Event Management | C35: V-0027 | D35: Extra Screens (sides & ceiling) - dimensions estimated | E35: 20 | F35: 1.5
A36: 02.25.C0180.102 | B36: Comtech Egypt Audio Visual Event Management | C36: V-0027 | D36: Media Server | E36: 1 | F36: 1.5
A37: 02.25.C0180.102 | B37: Comtech Egypt Audio Visual Event Management | C37: V-0027 | D37: Backdrop framing 2 screens + 1 banner in middle with acrylic logo/s & die cuts (totaling 14m width X 5 height) | E37: 1
A38: 02.25.C0180.102 | B38: Comtech Egypt Audio Visual Event Management | C38: V-0027 | D38: on ground screens for presenters & speakers - in sync with the main screen + 1 timer | E38: 3 | F38: 1
A39: 02.25.C0180.102 | B39: Comtech Egypt Audio Visual Event Management | C39: V-0027 | D39: Rental of professonal sound system ; high speakers, speakers surround, microphones (4 headsets + 2 handheld) , rack | E39: 1 | F39: 1
A40: 02.25.C0180.102 | B40: Comtech Egypt Audio Visual Event Management | C40: V-0027 | D40: Rental of professional light system (Clay Packy) - inclusive of moving heads, trusses, wash lights, beams, profiles, etc.. | E40: 1 | F40: 1
A41: 02.25.C0180.102 | B41: Comtech Egypt Audio Visual Event Management | C41: V-0027 | D41: LED Towers (each 1m width X 3m height) for messages, solgans, logo/s | E41: 4 | F41: 3
A42: 02.25.C0180.102 | B42: Comtech Egypt Audio Visual Event Management | C42: V-0027 | D42: LED / Plazma - 40inch - TV | E42: 4 | F42: 1.5
A43: 02.25.C0180.102 | B43: Comtech Egypt Audio Visual Event Management | C43: V-0027 | D43: LED / Plazma - 40inch - TV | E43: 1 | F43: 1.5
A44: 02.25.C0180.102 | B44: Comtech Egypt Audio Visual Event Management | C44: V-0027 | D44: Rental of professonal sound system including high speakers for background music | E44: 1 | F44: 1
A45: 02.25.C0180.102 | B45: Comtech Egypt Audio Visual Event Management | C45: V-0027 | D45: Rental of professional light system (Clay Packy) - wash light & effects + LED bars | E45: 1 | F45: 1
A46: 02.25.C0180.102 | B46: Comtech Egypt Audio Visual Event Management | C46: V-0027 | D46: LED Screens | E46: 4 | F46: 1.5
A47: 02.25.C0180.102 | B47: Comtech Egypt Audio Visual Event Management | C47: V-0027 | D47: Laptops | E47: 4 | F47: 1
A48: 02.25.C0180.102 | B48: Comtech Egypt Audio Visual Event Management | C48: V-0027 | D48: Monitors | E48: 4 | F48: 1
A49: 02.25.C0180.102 | B49: Comtech Egypt Audio Visual Event Management | C49: V-0027 | D49: Printers | E49: 4 | F49: 1
... A96: 02.25.C0006.103 | B96: Incentive House Of egypt | C96: V-0017 | D96: VAT on Management Fees | E96: 1 | F96: 1
A97: 02.25.C0006.103 | B97: Incentive House Of egypt | C97: V-0017 | D97: Management Fees | F97: 1
A98: 03.25.C0003.106 | B98: Incentive House Of egypt | C98: V-0017 | D98: Agency fees | E98: 1 | F98: 1
A99: 03.25.C0003.106 | B99: Incentive House Of egypt | C99: V-0017 | D99: VAT 14% | E99: 1 | F99: 1
A100: 02.25.C0180.102 | B100: Incentive House Of egypt | C100: V-0017 | D100: Management Fees | E100: 1 | F100: 1
A101: 02.25.C0003.104 | B101: Incentive House Of egypt | C101: V-0017 | D101: Management Fees | E101: 1 | F101: 1
A102: 04.25.C0006.107 | B102: Incentive House Of egypt | C102: V-0017 | D102: _Management Fees | E102: 1 | F102: 1
A103: 04.25.C0006.107 | B103: Incentive House Of egypt | C103: V-0017 | D103: _VAT on Management Fees | E103: 1 | F103: 1
A104: 05.25.C0202.108 | B104: Incentive House Of egypt | C104: V-0017 | D104: Management Fees | F104: 0.1
A105: 05.25.C0202.108 | B105: Incentive House Of egypt | C105: V-0017 | D105: VAT on Management fees | F105: 0.14
A106: 04.25.C0003.109 | B106: Incentive House Of egypt | C106: V-0017 | D106: Management Fees
A107: 04.25.C0003.110 | B107: Incentive House Of egypt | C107: V-0017 | D107: Management Fees & | E107: 0.1 | F107: 1
A108: 04.25.C0003.110 | B108: Incentive House Of egypt | C108: V-0017 | D108: VAT on Management Fees | E108: 0.14 | F108: 1
A109: 03.25.C0003.105 | B109: Incentive House Of egypt | C109: V-0017 | D109: Management Fees | E109: 1 | F109: 1
A110: 02.25.C0180.102 | B110: JACK ZAKARIA | C110: V-0459 | D110: for background music throughout the day - with 12 channels mixer | E110: 1 | F110: 1
A111: 02.25.C0180.102 | B111: JACK ZAKARIA | C111: V-0459 | D111: additional mixers for other areas | E111: 2 | F111: 1
A112: 04.25.C0006.107 | B112: KANJA | C112: V-0043 | D112: _Ushers | E112: 1 | F112: 1
A113: 03.25.C0003.106 | B113: DEAL COMPAMY | C113: V-0082 | D113: Ramadan Annual Sohour - Set Menu Where: Baron Palace - Laylina restaurant When: 18 March 2025 | E113: 60 | F113: 1
A114: 02.25.C0006.103 | B114: Local Arrangement | C114: #N/A | D114: Transportation via different method Tuk Tuk | E114: 20 | F114: 2
A115: 02.25.C0006.103 | B115: Local Arrangement | C115: #N/A | D115: Transportation via different method Tuk Tuk | E115: 20 | F115: 2
A116: 05.25.C0202.108 | B116: LOPO BEANCO BAG Trades ARROW (Ahmed Khairi) | C116: #N/A | D116: ** Beach Bag Package Includes :Beach Towel /Cap/Thermal Mug /bag with logo print | E116: 65 | F116: 1
A117: 02.25.C0006.103 | B117: Megumi Restaurant | C117: V-0063 | D117: Dinner at Megumi | E117: 28 | F117: 1
A118: 02.25.C0006.103 | B118: Movenpick Resort & Spa El Gouna | C118: V-0060 | D118: Half Day Meeting Meeting Room Usage | E118: 40 | F118: 1
A119: 02.25.C0006.103 | B119: Movenpick Resort & Spa El Gouna | C119: V-0060 | D119: Beverage Package ( 1 soft drink + 1 water) | E119: 28 | F119: 1
A120: 02.25.C0006.103 | B120: Movenpick Resort & Spa El Gouna | C120: V-0060 | D120: Beverage Package ( 1 soft drink + 1 water) | E120: 28 | F120: 1
A121: 02.25.C0006.103 | B121: Movenpick Resort & Spa El Gouna | C121: V-0060 | D121: Dinner at Smokery Restaurant | E121: 28 | F121: 1
A122: 02.25.C0006.103 | B122: Movenpick Resort & Spa El Gouna | C122: V-0060 | D122: Sea View Supplement - Per Room | E122: 2 | F122: 2
A123: 02.25.C0006.103 | B123: Movenpick Resort & Spa El Gouna | C123: V-0060 | D123: Lagoon view Supplement - Per Room | E123: 5 | F123: 2
A124: 02.25.C0006.103 | B124: Movenpick Resort & Spa El Gouna | C124: V-0060 | D124: Lagoon view Supplement - Per Room | E124: 8 | F124: 2
A125: 02.25.C0006.103 | B125: Movenpick Resort & Spa El Gouna | C125: V-0060 | D125: Per Person in Single room (garden view) | E125: 2 | F125: 2
A126: 02.25.C0006.103 | B126: Movenpick Resort & Spa El Gouna | C126: V-0060 | D126: Per Person sharing double (twin) room | E126: 10 | F126: 2
A127: 02.25.C0006.103 | B127: Movenpick Resort & Spa El Gouna | C127: V-0060 | D127: Per Person sharing double (twin) room | E127: 16 | F127: 2
A128: 02.25.C0006.103 | B128: NORTH AFRICA FOR SHIPMENT AND NASCO TOURS | C128: V-0002 | D128: Transportation to/from Marina | E128: 1 | F128: 2
... A136: 05.25.C0202.108 | B136: NORTH AFRICA FOR SHIPMENT AND NASCO TOURS | C136: V-0002 | D136: Pick-up from Hotel to be transferred to Sharm El Sheikh Airport cost per bus per way (2 buses are needed) | E136: 2 | F136: 1
A137: 04.25.C0003.109 | B137: NORTH AFRICA FOR SHIPMENT AND NASCO TOURS | C137: V-0002 | D137: Transportation Assembling & Dissembling
A138: 02.25.C0180.102 | B138: Production House | C138: V-0057 | D138: Poduim / Presenter Desk (specially designed with acrylic lighted logo) | E138: 1 | F138: 1
A139: 02.25.C0180.102 | B139: Production House | C139: V-0057 | D139: Side Banners | E139: 2 | F139: 1
A140: 02.25.C0180.102 | B140: Production House | C140: V-0057 | D140: Centerpieces - specially made with battery light / logo | E140: 30 | F140: 1
A141: 02.25.C0180.102 | B141: Production House | C141: V-0057 | D141: Branded Qubes (5 X 50cm) | E141: 5 | F141: 1
A142: 02.25.C0180.102 | B142: Production House | C142: V-0057 | D142: Branded Qubes (5 X 70cm) | E142: 5 | F142: 1
A143: 02.25.C0180.102 | B143: Production House | C143: V-0057 | D143: rental of 4 modern chairs (white) + 3 coffee tables | E143: Packaged
A144: 02.25.C0180.102 | B144: Production House | C144: V-0057 | D144: Production of : Backwall 3m width X 3m height + wooden 1 logo | E144: 4 | F144: 1
A145: 02.25.C0180.102 | B145: Production House | C145: V-0057 | D145: Furniture - 2 bar stools + 1 wide counter table (2m) + on side 1 high table | E145: 4 | F145: 1
A146: 02.25.C0180.102 | B146: Production House | C146: V-0057 | D146: Production of : Backwall 3m width X 3m height + wooden 1 logo | E146: 1 | F146: 1
A147: 02.25.C0180.102 | B147: Production House | C147: V-0057 | D147: Furniture - 2 bar stools + 1 wide counter table (2m) + on side 1 high table | E147: 1 | F147: 1
A148: 02.25.C0180.102 | B148: Production House | C148: V-0057 | D148: Wooden walls production between booths with 3D event logos | E148: 5 | F148: 1
A149: 02.25.C0180.102 | B149: Production House | C149: V-0057 | D149: high tables set (each 1 table with 4 chairs) | E149: 10 | F149: 1
A150: 02.25.C0180.102 | B150: Production House | C150: V-0057 | D150: 4m width X 3m height with die cut logo | E150: 1 | F150: 1
A151: 02.25.C0180.102 | B151: Production House | C151: V-0057 | D151: specially designed long desk - with backwall - diecuts & LED profiles lighting & acrylic logo | E151: 1 | F151: 1
A152: 02.25.C0180.102 | B152: Production House | C152: V-0057 | D152: e-invitation + QR - code / registration | E152: 1 | F152: 1
A153: 02.25.C0180.102 | B153: Production House | C153: V-0057 | D153: Photo Booth | E153: 1 | F153: 1
A154: 02.25.C0180.102 | B154: Production House | C154: V-0057 | D154: 3D Mockup | E154: 1 | F154: 1
A155: 02.25.C0180.102 | B155: Production House | C155: V-0057 | D155: 2 lounges - each 2 sofas (3 seaters but for 2) + 2 arm chairs | E155: 2 | F155: 1
...

Sheet Bud_Sal_Trxtbl
A1: PNR_ID | B1: Clnt_ID | C1: Item Des. | D1: Units | E1: no of nightsn | F1: Cost | G1: Gross Budget Sales VAT Included | H1: Currency | I1: Conversion
A2: 02.25.C0180.102 | B2: =MID(Bud_Sal_Trxtbl[[#This Row],[PNR_ID]],7,5) -> C0180 | C2: Ushers Totaling of (8F + 7M): | D2: 15 | E2: 1 | F2: 32 | G2: 547.2 | H2: USD | I2: 50.75
A3: 02.25.C0180.102 | B3: =MID(Bud_Sal_Trxtbl[[#This Row],[PNR_ID]],7,5) -> C0180 | C3: Ushers Uniforms - own black suit with white shirt - scarf for ladies / ties for gents | D3: 15 | E3: 1 | F3: 6.3 | G3: 107.73 | H3: USD | I3: 50.75
A4: 02.25.C0180.102 | B4: =MID(Bud_Sal_Trxtbl[[#This Row],[PNR_ID]],7,5) -> C0180 | C4: Option A : St. Regis - Steak House | D4: 25 | E4: 1 | F4: 165 | G4: 4702.5 | H4: USD | I4: 50.75
A5: 02.25.C0180.102 | B5: =MID(Bud_Sal_Trxtbl[[#This Row],[PNR_ID]],7,5) -> C0180 | C5: Rana Arafa | D5: 1 | E5: 1 | G5: 3249 | H5: USD | I5: 50.75
A6: 02.25.C0180.102 | B6: =MID(Bud_Sal_Trxtbl[[#This Row],[PNR_ID]],7,5) -> C0180 | C6: Poduim / Presenter Desk (specially designed with acrylic lighted logo) | D6: 1 | E6: 1 | F6: 235 | G6: 267.9 | H6: USD | I6: 50.75
A7: 02.25.C0180.102 | B7: =MID(Bud_Sal_Trxtbl[[#This Row],[PNR_ID]],7,5) -> C0180 | C7: Side Banners | D7: 2 | E7: 1 | F7: 265 | G7: 604.2 | H7: USD | I7: 50.75
A8: 02.25.C0180.102 | B8: =MID(Bud_Sal_Trxtbl[[#This Row],[PNR_ID]],7,5) -> C0180 | C8: Centerpieces - specially made with battery light / logo | D8: 30 | E8: 1 | F8: 40 | G8: 1368 | H8: USD | I8: 50.75
A9: 02.25.C0180.102 | B9: =MID(Bud_Sal_Trxtbl[[#This Row],[PNR_ID]],7,5) -> C0180 | C9: Branded Qubes (5 X 50cm) | D9: 5 | E9: 1 | F9: 65 | G9: 370.5 | H9: USD | I9: 50.75
A10: 02.25.C0180.102 | B10: =MID(Bud_Sal_Trxtbl[[#This Row],[PNR_ID]],7,5) -> C0180 | C10: Branded Qubes (5 X 70cm) | D10: 5 | E10: 1 | F10: 75 | G10: 427.5 | H10: USD | I10: 50.75
A11: 02.25.C0180.102 | B11: =MID(Bud_Sal_Trxtbl[[#This Row],[PNR_ID]],7,5) -> C0180 | C11: rental of 4 modern chairs (white) + 3 coffee tables | D11: Packaged | G11: 282.72 | H11: USD | I11: 50.75
A12: 02.25.C0180.102 | B12: =MID(Bud_Sal_Trxtbl[[#This Row],[PNR_ID]],7,5) -> C0180 | C12: Production of : Backwall 3m width X 3m height + wooden 1 logo | D12: 4 | E12: 1 | F12: 1445 | G12: 6589.2 | H12: USD | I12: 50.75
A13: 02.25.C0180.102 | B13: =MID(Bud_Sal_Trxtbl[[#This Row],[PNR_ID]],7,5) -> C0180 | C13: Furniture - 2 bar stools + 1 wide counter table (2m) + on side 1 high table | D13: 4 | E13: 1 | F13: 276 | G13: 1258.56 | H13: USD | I13: 50.75
A14: 02.25.C0180.102 | B14: =MID(Bud_Sal_Trxtbl[[#This Row],[PNR_ID]],7,5) -> C0180 | C14: Production of : Backwall 3m width X 3m height + wooden 1 logo | D14: 1 | E14: 1 | F14: 2410 | G14: 2747.4 | H14: USD | I14: 50.75
A15: 02.25.C0180.102 | B15: =MID(Bud_Sal_Trxtbl[[#This Row],[PNR_ID]],7,5) -> C0180 | C15: Furniture - 2 bar stools + 1 wide counter table (2m) + on side 1 high table | D15: 1 | E15: 1 | F15: 276 | G15: 314.64 | H15: USD | I15: 50.75
A16: 02.25.C0180.102 | B16: =MID(Bud_Sal_Trxtbl[[#This Row],[PNR_ID]],7,5) -> C0180 | C16: Wooden walls production between booths with 3D event logos | D16: 5 | E16: 1 | F16: 396 | G16: 2257.2 | H16: USD | I16: 50.75
A17: 02.25.C0180.102 | B17: =MID(Bud_Sal_Trxtbl[[#This Row],[PNR_ID]],7,5) -> C0180 | C17: high tables set (each 1 table with 4 chairs) | D17: 10 | E17: 1 | F17: 87.6 | G17: 998.64 | H17: USD | I17: 50.75
A18: 02.25.C0180.102 | B18: =MID(Bud_Sal_Trxtbl[[#This Row],[PNR_ID]],7,5) -> C0180 | C18: 4m width X 3m height with die cut logo | D18: 1 | E18: 1 | G18: 969 | H18: USD | I18: 50.75
A19: 02.25.C0180.102 | B19: =MID(Bud_Sal_Trxtbl[[#This Row],[PNR_ID]],7,5) -> C0180 | C19: specially designed long desk - with backwall - diecuts & LED profiles lighting & acrylic logo | D19: 1 | E19: 1 | F19: 1500 | G19: 1710 | H19: USD | I19: 50.75
A20: 02.25.C0180.102 | B20: =MID(Bud_Sal_Trxtbl[[#This Row],[PNR_ID]],7,5) -> C0180 | C20: e-invitation + QR - code / registration | D20: 1 | E20: 1 | F20: 250 | G20: 285 | H20: USD | I20: 50.75
A21: 02.25.C0180.102 | B21: =MID(Bud_Sal_Trxtbl[[#This Row],[PNR_ID]],7,5) -> C0180 | C21: Photo Booth | D21: 1 | E21: 1 | G21: 1687.2 | H21: USD | I21: 50.75
A22: 02.25.C0180.102 | B22: =MID(Bud_Sal_Trxtbl[[#This Row],[PNR_ID]],7,5) -> C0180 | C22: 3D Mockup | D22: 1 | E22: 1 | G22: 963.3 | H22: USD | I22: 50.75
A23: 02.25.C0180.102 | B23: =MID(Bud_Sal_Trxtbl[[#This Row],[PNR_ID]],7,5) -> C0180 | C23: 2 lounges - each 2 sofas (3 seaters but for 2) + 2 arm chairs | D23: 2 | E23: 1 | F23: 247 | G23: 563.16 | H23: USD | I23: 50.75
A24: 02.25.C0180.102 | B24: =MID(Bud_Sal_Trxtbl[[#This Row],[PNR_ID]],7,5) -> C0180 | C24: ** Designing fees - 3D | D24: 1 | E24: 1 | G24: 1140 | H24: USD | I24: 50.75
A25: 02.25.C0180.102 | B25: =MID(Bud_Sal_Trxtbl[[#This Row],[PNR_ID]],7,5) -> C0180 | C25: ** Transportation & assembling / disambling of : (screens, AV, stages, production, …) | D25: 1 | E25: 1 | G25: 1710 | H25: USD | I25: 50.75
A26: 02.25.C0180.102 | B26: =MID(Bud_Sal_Trxtbl[[#This Row],[PNR_ID]],7,5) -> C0180 | C26: Name Tags &Lanyards | D26: 220 | E26: 1 | F26: 3.2 | G26: 802.56 | H26: USD | I26: 50.75
A27: 02.25.C0180.102 | B27: =MID(Bud_Sal_Trxtbl[[#This Row],[PNR_ID]],7,5) -> C0180 | C27: Direction Signs | D27: 8 | E27: 1 | F27: 68 | G27: 620.16 | H27: USD | I27: 50.75
A28: 02.25.C0180.102 | B28: =MID(Bud_Sal_Trxtbl[[#This Row],[PNR_ID]],7,5) -> C0180 | C28: Shirts with embroiderad 2 logos | D28: 20 | E28: 1 | F28: 10.5 | G28: 239.4 | H28: USD | I28: 50.75
A29: 02.25.C0180.102 | B29: =MID(Bud_Sal_Trxtbl[[#This Row],[PNR_ID]],7,5) -> C0180 | C29: Printing of Special Parking Cards | D29: 250 | E29: 1 | F29: 1.5 | G29: 427.5 | H29: USD | I29: 50.75
A30: 02.25.C0180.102 | B30: =MID(Bud_Sal_Trxtbl[[#This Row],[PNR_ID]],7,5) -> C0180 | C30: for background music throughout the day - with 12 channels mixer | D30: 1 | E30: 1 | F30: 320 | G30: 364.8 | H30: USD | I30: 50.75
A31: 02.25.C0180.102 | B31: =MID(Bud_Sal_Trxtbl[[#This Row],[PNR_ID]],7,5) -> C0180 | C31: additional mixers for other areas | D31: 2 | E31: 1 | F31: 120 | G31: 273.6 | H31: USD | I31: 50.75
A32: 02.25.C0180.102 | B32: =MID(Bud_Sal_Trxtbl[[#This Row],[PNR_ID]],7,5) -> C0180 | C32: 2 main LED screens on sides (each 4m width X 3m height) - totaling 24 meters screens | D32: 24 | E32: 1.5 | F32: 31.7 | G32: 1300.968 | H32: USD | I32: 50.75
A33: 02.25.C0180.102 | B33: =MID(Bud_Sal_Trxtbl[[#This Row],[PNR_ID]],7,5) -> C0180 | C33: Extra Screens (sides & ceiling) - dimensions estimated | D33: 20 | E33: 1.5 | F33: 31.7 | G33: 1084.14 | H33: USD | I33: 50.75
A34: 02.25.C0180.102 | B34: =MID(Bud_Sal_Trxtbl[[#This Row],[PNR_ID]],7,5) -> C0180 | C34: Media Server | D34: 1 | E34: 1.5 | F34: 380.5 | G34: 650.655 | H34: USD | I34: 50.75
A35: 02.25.C0180.102 | B35: =MID(Bud_Sal_Trxtbl[[#This Row],[PNR_ID]],7,5) -> C0180 | C35: Backdrop framing 2 screens + 1 banner in middle with acrylic logo/s & die cuts (totaling 14m width X 5 height) | D35: 1 | G35: 4702.5 | H35: USD | I35: 50.75
A36: 02.25.C0180.102 | B36: =MID(Bud_Sal_Trxtbl[[#This Row],[PNR_ID]],7,5) -> C0180 | C36: on ground screens for presenters & speakers - in sync with the main screen + 1 timer | D36: 3 | E36: 1 | F36: 42.5 | G36: 145.35 | H36: USD | I36: 50.75
A37: 02.25.C0180.102 | B37: =MID(Bud_Sal_Trxtbl[[#This Row],[PNR_ID]],7,5) -> C0180 | C37: Rental of professonal sound system ; high speakers, speakers surround, microphones (4 headsets + 2 handheld) , rack | D37: 1 | E37: 1 | G37: 1083 | H37: USD | I37: 50.75
A38: 02.25.C0180.102 | B38: =MID(Bud_Sal_Trxtbl[[#This Row],[PNR_ID]],7,5) -> C0180 | C38: Rental of professional light system (Clay Packy) - inclusive of moving heads, trusses, wash lights, beams, profiles, etc.. | D38: 1 | E38: 1 | G38: 1368 | H38: USD | I38: 50.75
A39: 02.25.C0180.102 | B39: =MID(Bud_Sal_Trxtbl[[#This Row],[PNR_ID]],7,5) -> C0180 | C39: LED Towers (each 1m width X 3m height) for messages, solgans, logo/s | D39: 4 | E39: 3 | F39: 31.7 | G39: 433.656 | H39: USD | I39: 50.75
A40: 02.25.C0180.102 | B40: =MID(Bud_Sal_Trxtbl[[#This Row],[PNR_ID]],7,5) -> C0180 | C40: LED / Plazma - 40inch - TV | D40: 4 | E40: 1.5 | F40: 55 | G40: 376.2 | H40: USD | I40: 50.75
A41: 02.25.C0180.102 | B41: =MID(Bud_Sal_Trxtbl[[#This Row],[PNR_ID]],7,5) -> C0180 | C41: LED / Plazma - 40inch - TV | D41: 1 | E41: 1.5 | F41: 55 | G41: 94.05 | H41: USD | I41: 50.75
A42: 02.25.C0180.102 | B42: =MID(Bud_Sal_Trxtbl[[#This Row],[PNR_ID]],7,5) -> C0180 | C42: Rental of professonal sound system including high speakers for background music | D42: 1 | E42: 1 | G42: 484.5 | H42: USD | I42: 50.75
A43: 02.25.C0180.102 | B43: =MID(Bud_Sal_Trxtbl[[#This Row],[PNR_ID]],7,5) -> C0180 | C43: Rental of professional light system (Clay Packy) - wash light & effects + LED bars | D43: 1 | E43: 1 | G43: 729.6 | H43: USD | I43: 50.75
A44: 02.25.C0180.102 | B44: =MID(Bud_Sal_Trxtbl[[#This Row],[PNR_ID]],7,5) -> C0180 | C44: LED Screens | D44: 4 | E44: 1.5 | F44: 55 | G44: 376.2 | H44: USD | I44: 50.75
A45: 02.25.C0180.102 | B45: =MID(Bud_Sal_Trxtbl[[#This Row],[PNR_ID]],7,5) -> C0180 | C45: Laptops | D45: 4 | E45: 1 | F45: 42.3 | G45: 192.888 | H45: USD | I45: 50.75
A46: 02.25.C0180.102 | B46: =MID(Bud_Sal_Trxtbl[[#This Row],[PNR_ID]],7,5) -> C0180 | C46: Monitors | D46: 4 | E46: 1 | F46: 32 | G46: 145.92 | H46: USD | I46: 50.75
A47: 02.25.C0180.102 | B47: =MID(Bud_Sal_Trxtbl[[#This Row],[PNR_ID]],7,5) -> C0180 | C47: Printers | D47: 4 | E47: 1 | F47: 30 | G47: 136.8 | H47: USD | I47: 50.75
A48: 02.25.C0180.102 | B48: =MID(Bud_Sal_Trxtbl[[#This Row],[PNR_ID]],7,5) -> C0180 | C48: Separators | D48: 4 | E48: 1 | F48: 10.5 | G48: 47.88 | H48: USD | I48: 50.75
A49: 02.25.C0180.102 | B49: =MID(Bud_Sal_Trxtbl[[#This Row],[PNR_ID]],7,5) -> C0180 | C49: Gate including LED arch | D49: 1 | E49: 1.5 | F49: 1100 | G49: 1881 | H49: USD | I49: 50.75
A50: 02.25.C0180.102 | B50: =MID(Bud_Sal_Trxtbl[[#This Row],[PNR_ID]],7,5) -> C0180 | C50: LED Towers (with the agenda & logos) - each 1m width X 3m height | D50: 4 | E50: 3 | F50: 31.7 | G50: 433.656 | H50: USD | I50: 50.75
A51: 02.25.C0180.102 | B51: =MID(Bud_Sal_Trxtbl[[#This Row],[PNR_ID]],7,5) -> C0180 | C51: Sound system (background music) | D51: 1 | E51: 1 | G51: 433.2 | H51: USD | I51: 50.75
A52: 02.25.C0180.102 | B52: =MID(Bud_Sal_Trxtbl[[#This Row],[PNR_ID]],7,5) -> C0180 | C52: Light System | D52: 1 | E52: 1 | G52: 598.5 | H52: USD | I52: 50.75
A53: 02.25.C0180.102 | B53: =MID(Bud_Sal_Trxtbl[[#This Row],[PNR_ID]],7,5) -> C0180 | C53: 1 LED Tower - 1m width X 3m height | D53: 1 | E53: 3 | F53: 31.7 | G53: 108.414 | H53: USD | I53: 50.75
A54: 02.25.C0180.102 | B54: =MID(Bud_Sal_Trxtbl[[#This Row],[PNR_ID]],7,5) -> C0180 | C54: Media wall (3m X 2m) for greetings & photos | D54: 1 | E54: 1 | F54: 485 | G54: 552.9 | H54: USD | I54: 50.75
A55: 02.25.C0180.102 | B55: =MID(Bud_Sal_Trxtbl[[#This Row],[PNR_ID]],7,5) -> C0180 | C55: Photo Shooting | D55: 1 | E55: 1 | G55: 484.5 | H55: USD | I55: 50.75
A56: 02.25.C0180.102 | B56: =MID(Bud_Sal_Trxtbl[[#This Row],[PNR_ID]],7,5) -> C0180 | C56: Video Shooting | D56: 1 | E56: 1 | G56: 604.2 | H56: USD | I56: 50.75
A57: 02.25.C0180.102 | B57: =MID(Bud_Sal_Trxtbl[[#This Row],[PNR_ID]],7,5) -> C0180 | C57: Promo Movie : 2-3min movie for the whole event & main highlights with montage & effects | D57: 1 | E57: 1 | G57: 741 | H57: USD | I57: 50.75
A58: 02.25.C0180.102 | B58: =MID(Bud_Sal_Trxtbl[[#This Row],[PNR_ID]],7,5) -> C0180 | C58: Photo Printing - on spot | D58: 1 | E58: 1 | G58: 250.8 | H58: USD | I58: 50.75
A59: 02.25.C0180.102 | B59: =MID(Bud_Sal_Trxtbl[[#This Row],[PNR_ID]],7,5) -> C0180 | C59: Management Fees | D59: 1 | E59: 1 | F59: 1 | G59: 5757.9747 | H59: USD | I59: 50.75
A60: 02.25.C0006.103 | B60: =MID(Bud_Sal_Trxtbl[[#This Row],[PNR_ID]],7,5) -> C0006 | C60: Transportation via different method Tuk Tuk | D60: 20 | E60: 2 | F60: 68.25 | G60: 2730 | H60: EGP | I60: 1
A61: 02.25.C0006.103 | B61: =MID(Bud_Sal_Trxtbl[[#This Row],[PNR_ID]],7,5) -> C0006 | C61: Transportation via different method Tuk Tuk | D61: 20 | E61: 2 | F61: 68.25 | G61: 2730 | H61: EGP | I61: 1
A62: 02.25.C0006.103 | B62: =MID(Bud_Sal_Trxtbl[[#This Row],[PNR_ID]],7,5) -> C0006 | C62: Transportation to/from Marina | D62: 1 | E62: 2 | F62: 8662.5 | G62: 17325 | H62: EGP | I62: 1
A63: 02.25.C0006.103 | B63: =MID(Bud_Sal_Trxtbl[[#This Row],[PNR_ID]],7,5) -> C0006 | C63: full dedicated escort throughout the event (from/to Cairo) | D63: 1 | E63: 1 | F63: 29150 | G63: 29150 | H63: EGP | I63: 1
A64: 02.25.C0006.103 | B64: =MID(Bud_Sal_Trxtbl[[#This Row],[PNR_ID]],7,5) -> C0006 | C64: Minii Van from/to Cairo - - cost per vehicle per way | D64: 4 | E64: 2 | F64: 15000 | G64: 120000 | H64: EGP | I64: 1
A65: 02.25.C0006.103 | B65: =MID(Bud_Sal_Trxtbl[[#This Row],[PNR_ID]],7,5) -> C0006 | C65: Minii Van from/to Cairo - - cost per vehicle per way VAT | D65: 1 | E65: 1 | F65: 16800 | G65: 16800 | H65: EGP | I65: 1
A66: 02.25.C0006.103 | B66: =MID(Bud_Sal_Trxtbl[[#This Row],[PNR_ID]],7,5) -> C0006 | C66: VAT on Management Fees | D66: 1 | E66: 1 | F66: 13284.11 | G66: 13284.11 | H66: EGP | I66: 1
A67: 02.25.C0006.103 | B67: =MID(Bud_Sal_Trxtbl[[#This Row],[PNR_ID]],7,5) -> C0006 | C67: Management Fees | E67: 1 | F67: 94886.5 | G67: 94886.5 | H67: EGP | I67: 1
A68: 02.25.C0006.103 | B68: =MID(Bud_Sal_Trxtbl[[#This Row],[PNR_ID]],7,5) -> C0006 | C68: Basic Meeting Equipment (stage + LED screen 3 X 2 + sound system with 2 wirless mics) | D68: 1 | E68: 1 | F68: 19950 | G68: 19950 | H68: EGP | I68: 1
A69: 02.25.C0006.103 | B69: =MID(Bud_Sal_Trxtbl[[#This Row],[PNR_ID]],7,5) -> C0006 | C69: Half Day Meeting Meeting Room Usage | D69: 40 | E69: 1 | F69: 2887.5 | G69: 115500 | H69: EGP | I69: 1
A70: 02.25.C0006.103 | B70: =MID(Bud_Sal_Trxtbl[[#This Row],[PNR_ID]],7,5) -> C0006 | C70: Dinner at Megumi | D70: 28 | E70: 1 | F70: 3200 | G70: 89600 | H70: EGP | I70: 1
A71: 02.25.C0006.103 | B71: =MID(Bud_Sal_Trxtbl[[#This Row],[PNR_ID]],7,5) -> C0006 | C71: Beverage Package ( 1 soft drink + 1 water) | D71: 28 | E71: 1 | F71: 236.25 | G71: 6615 | H71: EGP | I71: 1
A72: 02.25.C0006.103 | B72: =MID(Bud_Sal_Trxtbl[[#This Row],[PNR_ID]],7,5) -> C0006 | C72: Beverage Package ( 1 soft drink + 1 water) | D72: 28 | E72: 1 | F72: 315 | G72: 8820 | H72: EGP | I72: 1
A73: 02.25.C0006.103 | B73: =MID(Bud_Sal_Trxtbl[[#This Row],[PNR_ID]],7,5) -> C0006 | C73: Dinner at Smokery Restaurant | D73: 28 | E73: 1 | F73: 2100 | G73: 58800 | H73: EGP | I73: 1
A74: 02.25.C0006.103 | B74: =MID(Bud_Sal_Trxtbl[[#This Row],[PNR_ID]],7,5) -> C0006 | C74: Boat Trip | D74: 40 | E74: 1 | F74: 5145 | G74: 205800 | H74: EGP | I74: 1
A75: 02.25.C0006.103 | B75: =MID(Bud_Sal_Trxtbl[[#This Row],[PNR_ID]],7,5) -> C0006 | C75: Sea View Supplement - Per Room | D75: 2 | E75: 2 | F75: 1050 | G75: 4200 | H75: EGP | I75: 1
A76: 02.25.C0006.103 | B76: =MID(Bud_Sal_Trxtbl[[#This Row],[PNR_ID]],7,5) -> C0006 | C76: Lagoon view Supplement - Per Room | D76: 5 | E76: 2 | F76: 787.5 | G76: 7875 | H76: EGP | I76: 1
A77: 02.25.C0006.103 | B77: =MID(Bud_Sal_Trxtbl[[#This Row],[PNR_ID]],7,5) -> C0006 | C77: Lagoon view Supplement - Per Room | D77: 8 | E77: 2 | F77: 787.5 | G77: 12600 | H77: EGP | I77: 1
A78: 02.25.C0006.103 | B78: =MID(Bud_Sal_Trxtbl[[#This Row],[PNR_ID]],7,5) -> C0006 | C78: Per Person in Single room (garden view) | D78: 2 | E78: 2 | F78: 7980 | G78: 31920 | H78: EGP | I78: 1
A79: 02.25.C0006.103 | B79: =MID(Bud_Sal_Trxtbl[[#This Row],[PNR_ID]],7,5) -> C0006 | C79: Per Person sharing double (twin) room | D79: 10 | E79: 2 | F79: 4462.5 | G79: 89250 | H79: EGP | I79: 1
... A85: 03.25.C0003.105 | B85: =MID(Bud_Sal_Trxtbl[[#This Row],[PNR_ID]],7,5) -> C0003 | C85: Management Fees | D85: 1 | E85: 1 | F85: 32821.74 | G85: 32821.74 | H85: EGP | I85: 1
A86: 03.25.C0003.105 | B86: =MID(Bud_Sal_Trxtbl[[#This Row],[PNR_ID]],7,5) -> C0003 | C86: Beverages Package for 2 hours | D86: 45 | E86: 1 | G86: 32760 | H86: EGP | I86: 1
A87: 03.25.C0003.105 | B87: =MID(Bud_Sal_Trxtbl[[#This Row],[PNR_ID]],7,5) -> C0003 | C87: Special Parking Cards | D87: 50 | E87: 1 | F87: 425 | G87: 21250 | H87: EGP | I87: 1
A88: 03.25.C0003.105 | B88: =MID(Bud_Sal_Trxtbl[[#This Row],[PNR_ID]],7,5) -> C0003 | C88: Wifi cards | D88: 10 | E88: 1 | F88: 470 | G88: 4700 | H88: EGP | I88: 1
A89: 03.25.C0003.105 | B89: =MID(Bud_Sal_Trxtbl[[#This Row],[PNR_ID]],7,5) -> C0003 | C89: Sohour meal | D89: 45 | E89: 1 | G89: 140400 | H89: EGP | I89: 1
A90: 03.25.C0003.105 | B90: =MID(Bud_Sal_Trxtbl[[#This Row],[PNR_ID]],7,5) -> C0003 | C90: Standard Round tables + banquet chairs - covered with abailable table cloth & chairs covers | D90: 6 | E90: 1 | F90: Provided by hotel | G90: 0 | H90: EGP | I90: 1
A91: 03.25.C0003.105 | B91: =MID(Bud_Sal_Trxtbl[[#This Row],[PNR_ID]],7,5) -> C0003 | C91: Crystal Trophy with engraving or print | D91: 1 | E91: 1 | F91: 2500 | G91: 2500 | H91: EGP | I91: 1
A92: 03.25.C0003.105 | B92: =MID(Bud_Sal_Trxtbl[[#This Row],[PNR_ID]],7,5) -> C0003 | C92: Plexi black stage 7m width X 2m depth X 0.4m height | D92: 1 | E92: 1 | F92: 11800 | G92: 11800 | H92: EGP | I92: 1
A93: 03.25.C0003.105 | B93: =MID(Bud_Sal_Trxtbl[[#This Row],[PNR_ID]],7,5) -> C0003 | C93: LED screen - for multi usage of presentation & as branding backdrop / P2 - 3m width X 2m height | D93: 6 | E93: 1 | F93: 1700 | G93: 10200 | H93: EGP | I93: 1
A94: 03.25.C0003.105 | B94: =MID(Bud_Sal_Trxtbl[[#This Row],[PNR_ID]],7,5) -> C0003 | C94: 2 side screens each 1.5m width X 2m height | D94: 6 | E94: 1 | F94: 1700 | G94: 10200 | H94: EGP | I94: 1
A95: 03.25.C0003.105 | B95: =MID(Bud_Sal_Trxtbl[[#This Row],[PNR_ID]],7,5) -> C0003 | C95: Lighting | D95: 1 | E95: 1 | F95: NR | G95: 0 | H95: EGP | I95: 1
A96: 03.25.C0003.105 | B96: =MID(Bud_Sal_Trxtbl[[#This Row],[PNR_ID]],7,5) -> C0003 | C96: 1- Poduim | D96: 1 | E96: 1 | F96: 6500 | G96: 6500 | H96: EGP | I96: 1
A97: 03.25.C0003.105 | B97: =MID(Bud_Sal_Trxtbl[[#This Row],[PNR_ID]],7,5) -> C0003 | C97: Basic Sound System - with 2 wireless mics | D97: 1 | E97: 1 | F97: 9900 | G97: 9900 | H97: EGP | I97: 1
A98: 03.25.C0003.105 | B98: =MID(Bud_Sal_Trxtbl[[#This Row],[PNR_ID]],7,5) -> C0003 | C98: 2- LED Towers (each 1m width X 3m height) | D98: 2 | E98: 3 | F98: 1700 | G98: 10200 | H98: EGP | I98: 1
A99: 03.25.C0003.105 | B99: =MID(Bud_Sal_Trxtbl[[#This Row],[PNR_ID]],7,5) -> C0003 | C99: Video Shooting | D99: 1 | E99: 1 | F99: 10000 | G99: 10000 | H99: EGP | I99: 1
A100: 03.25.C0003.105 | B100: =MID(Bud_Sal_Trxtbl[[#This Row],[PNR_ID]],7,5) -> C0003 | C100: Promo Movie : 2-3min movie for the whole event & main highlights with montage & effects | D100: 1 | E100: 1 | F100: 8000 | G100: 8000 | H100: EGP | I100: 1
A101: 03.25.C0003.105 | B101: =MID(Bud_Sal_Trxtbl[[#This Row],[PNR_ID]],7,5) -> C0003 | C101: Photo Shooting | D101: 1 | E101: 1 | F101: 8000 | G101: 8000 | H101: EGP | I101: 1
A102: 03.25.C0003.106 | B102: =MID(Bud_Sal_Trxtbl[[#This Row],[PNR_ID]],7,5) -> C0003 | C102: Ramadan Annual Sohour - Set Menu Where: Baron Palace - Laylina restaurant When: 18 March 2025 | D102: 60 | E102: 1 | F102: 3036.6 | G102: 182196 | H102: EGP | I102: 1
A103: 03.25.C0003.106 | B103: =MID(Bud_Sal_Trxtbl[[#This Row],[PNR_ID]],7,5) -> C0003 | C103: Agency fees | D103: 1 | E103: 1 | F103: 12146.4 | G103: 12146.4 | H103: EGP | I103: 1
A104: 03.25.C0003.106 | B104: =MID(Bud_Sal_Trxtbl[[#This Row],[PNR_ID]],7,5) -> C0003 | C104: VAT 14% | D104: 1 | E104: 1 | F104: 1700.496 | G104: 1700.496 | H104: EGP | I104: 1
A105: 04.25.C0006.107 | B105: =MID(Bud_Sal_Trxtbl[[#This Row],[PNR_ID]],7,5) -> C0006 | C105: Stage Monitor on ground screens for presenters & speakers - in sync with th | D105: 1 | E105: 1 | F105: 2381.6 | G105: 2381.6 | H105: EGP | I105: 1
...
